Workbook

Sheet Resumen
A1: Estados financieros - Berts Solutions SL
A2: Generado el 22/09/2026 con scripts/generar_informes.py a partir de /datos/. No se edita a mano: se vuelve a generar con cada actualización.
B4: Fecha de corte del balance | C4: 46287 | D4: Puedes poner una fecha ANTERIOR para ver el balance a ese día. Para una fecha posterior, vuelve a generar el informe (la amortización se calcula hasta la fecha de generación).
B5: Fecha comparativa (último cierre) | C5: 46022
B7: Cifras clave a la fecha de corte | C7: Importe (€) | D7: Qué significa
B8: Total activo (lo que tiene la empresa) | C8: =Balance!D21 -> 92959.82 | D8: Vehículos (neto de amortización) + dinero + lo que le deben.
B9: Tesorería según contabilidad | C9: =Balance!D20 -> 52415.82 | D9: Debería coincidir con el extracto del BBVA. Sin extractos no está comprobado.
B10: Vehículos (valor neto contable) | C10: =Balance!D7 -> 32340.84 | D10: Coste de los vehículos menos la amortización acumulada.
B11: Clientes pendientes de cobro | C11: =Balance!D15 -> 4890.85 | D11: Facturas emitidas que no nos consta que se hayan cobrado.
B12: Patrimonio neto (lo que es de los socios) | C12: =Balance!D24 -> 67535.82 | D12: Capital + aportaciones + resultados acumulados.
B13: Partidas pendientes de aplicación (cuenta 555) | C13: =Balance!D36 -> 24498.06 | D13: Pagos cuyo origen desconocemos. Tiene que llegar a 0 cuando tengamos los extractos.
B14: Ingresos por alquiler del ejercicio | C14: =PyG!H8 -> 1737.73 | D14: Cifra de negocios acumulada.
B15: Resultado del ejercicio (beneficio / pérdida) | C15: =PyG!H26 -> -7782.79 | D15: Ingresos menos todos los gastos, incluida la amortización y la pérdida del Ford Fiesta.
B17: Controles de cuadre | C17: Diferencia (€) | D17: Estado
B18: Activo = Patrimonio neto + Pasivo | C18: =Balance!D21-Balance!D41 -> 0 | D18: =IF(ABS(C18)<0.01,"OK","ERROR - revisar") -> OK
B19: Libro diario: Debe = Haber | C19: =Diario!F231-Diario!G231 -> 0 | D19: =IF(ABS(C19)<0.01,"OK","ERROR - revisar") -> OK
B20: Resultado de la PyG = Resultado del balance | C20: =PyG!H26-Balance!D29 -> 0 | D20: =IF(ABS(C20)<0.01,"OK","ERROR - revisar") -> OK
B21: Balance 31/12/2025 = el de Fisama (75.318,61 €) | C21: =Balance!C21-75318.61 -> 0 | D21: =IF(ABS(C21)<0.01,"OK","ERROR - revisar") -> OK
B23: Hojas de este libro
B24: Balance | D24: Balance de situación (modelo PGC Pymes) a 31/12/2025 y a la fecha de corte.
B25: PyG | D25: Cuenta de pérdidas y ganancias por trimestres + detalle por cuenta.
B26: Vehículos | D26: Coste, amortización, valor neto y resultado de cada vehículo.
B27: IVA | D27: IVA repercutido y soportado por trimestre, para contrastar con el modelo 303.
B28: Pendiente | D28: 19 avisos: información que falta o no cuadra.
B29: Diario | D29: Libro diario: todos los asientos. Todo lo demás sale de aquí.
B30: Sumas y saldos | D30: Saldo de cada cuenta contable.
B31: Plan de cuentas | D31: Qué cuenta va a qué línea del balance y de la PyG.
B33: Leyenda de colores
B34: Azul: dato introducido (fecha de corte, cifras de Fisama, precios de compra).
B35: Negro: fórmula calculada a partir del Diario.
B36: Verde: enlace a otra hoja de este libro.
B37: Fondo amarillo: celda que puedes cambiar.

Sheet Balance
A1: Balance de Situación - Berts Solutions SL (CIF B23928419)
A2: Modelo PGC Pymes. Todas las cifras salen del Diario con fórmulas. La columna del 31/12/2025 reproduce el balance presentado por Fisama.
B4: ACTIVO | C4: =FechaComparativa -> 46022 | D4: =FechaCorte -> 46287
A5: A | B5: A) ACTIVO NO CORRIENTE | C5: =C6+C7+C11 -> 9192 | D5: =D6+D7+D11 -> 32340.84
A6: AI | B6: I. Inmovilizado intangible | C6: =SUMIFS(Diario!$K$2:$K$229,Diario!$L$2:$L$229,"AI",Diario!$B$2:$B$229,"<="&C$4) -> 0 | D6: =SUMIFS(Diario!$K$2:$K$229,Diario!$L$2:$L$229,"AI",Diario!$B$2:$B$229,"<="&D$4) -> 0
A7: AII | B7: II. Inmovilizado material | C7: =C8+C9+C10 -> 9192 | D7: =D8+D9+D10 -> 32340.84
A8: AII1 | B8: Elementos de transporte (vehículos) | C8: =SUMIFS(Diario!$K$2:$K$229,Diario!$L$2:$L$229,"AII1",Diario!$B$2:$B$229,"<="&C$4) -> 0 | D8: =SUMIFS(Diario!$K$2:$K$229,Diario!$L$2:$L$229,"AII1",Diario!$B$2:$B$229,"<="&D$4) -> 33790.93
A9: AII2 | B9: Otro inmovilizado material | C9: =SUMIFS(Diario!$K$2:$K$229,Diario!$L$2:$L$229,"AII2",Diario!$B$2:$B$229,"<="&C$4) -> 9192 | D9: =SUMIFS(Diario!$K$2:$K$229,Diario!$L$2:$L$229,"AII2",Diario!$B$2:$B$229,"<="&D$4) -> 0
A10: AII3 | B10: Amortización acumulada | C10: =SUMIFS(Diario!$K$2:$K$229,Diario!$L$2:$L$229,"AII3",Diario!$B$2:$B$229,"<="&C$4) -> 0 | D10: =SUMIFS(Diario!$K$2:$K$229,Diario!$L$2:$L$229,"AII3",Diario!$B$2:$B$229,"<="&D$4) -> -1450.09
A11: AV | B11: V. Inversiones financieras a largo plazo | C11: =SUMIFS(Diario!$K$2:$K$229,Diario!$L$2:$L$229,"AV",Diario!$B$2:$B$229,"<="&C$4) -> 0 | D11: =SUMIFS(Diario!$K$2:$K$229,Diario!$L$2:$L$229,"AV",Diario!$B$2:$B$229,"<="&D$4) -> 0
A12: B | B12: B) ACTIVO CORRIENTE | C12: =C13+C14+C19+C20 -> 66126.61 | D12: =D13+D14+D19+D20 -> 60618.98
A13: BII | B13: II. Existencias | C13: =SUMIFS(Diario!$K$2:$K$229,Diario!$L$2:$L$229,"BII",Diario!$B$2:$B$229,"<="&C$4) -> 0 | D13: =SUMIFS(Diario!$K$2:$K$229,Diario!$L$2:$L$229,"BII",Diario!$B$2:$B$229,"<="&D$4) -> 0
A14: BIII | B14: III. Deudores comerciales y otras cuentas a cobrar | C14: =C15+C16+C17+C18 -> 0 | D14: =D15+D16+D17+D18 -> 8203.16
A15: BIII1 | B15: 1. Clientes por ventas y prestaciones de servicios | C15: =SUMIFS(Diario!$K$2:$K$229,Diario!$L$2:$L$229,"BIII1",Diario!$B$2:$B$229,"<="&C$4) -> 0 | D15: =SUMIFS(Diario!$K$2:$K$229,Diario!$L$2:$L$229,"BIII1",Diario!$B$2:$B$229,"<="&D$4) -> 4890.85
A16: BIII2 | B16: 2. Hacienda Pública deudora (IVA soportado / a compensar) | C16: =SUMIFS(Diario!$K$2:$K$229,Diario!$L$2:$L$229,"BIII2",Diario!$B$2:$B$229,"<="&C$4) -> 0 | D16: =SUMIFS(Diario!$K$2:$K$229,Diario!$L$2:$L$229,"BIII2",Diario!$B$2:$B$229,"<="&D$4) -> 3312.31
A17: BIII3 | B17: 3. Socios deudores | C17: =MAX(0,SUMIFS(Diario!$K$2:$K$229,Diario!$L$2:$L$229,"D551",Diario!$B$2:$B$229,"<="&C$4)) -> 0 | D17: =MAX(0,SUMIFS(Diario!$K$2:$K$229,Diario!$L$2:$L$229,"D551",Diario!$B$2:$B$229,"<="&D$4)) -> 0
A18: BIII4 | B18: 4. Partidas pendientes de aplicación (saldo deudor) | C18: =MAX(0,SUMIFS(Diario!$K$2:$K$229,Diario!$L$2:$L$229,"D555",Diario!$B$2:$B$229,"<="&C$4)) -> 0 | D18: =MAX(0,SUMIFS(Diario!$K$2:$K$229,Diario!$L$2:$L$229,"D555",Diario!$B$2:$B$229,"<="&D$4)) -> 0
A19: BVI | B19: VI. Periodificaciones a corto plazo | C19: =SUMIFS(Diario!$K$2:$K$229,Diario!$L$2:$L$229,"BVI",Diario!$B$2:$B$229,"<="&C$4) -> 0 | D19: =SUMIFS(Diario!$K$2:$K$229,Diario!$L$2:$L$229,"BVI",Diario!$B$2:$B$229,"<="&D$4) -> 0
A20: BVII | B20: VII. Efectivo y otros activos líquidos equivalentes | C20: =SUMIFS(Diario!$K$2:$K$229,Diario!$L$2:$L$229,"BVII",Diario!$B$2:$B$229,"<="&C$4) -> 66126.61 | D20: =SUMIFS(Diario!$K$2:$K$229,Diario!$L$2:$L$229,"BVII",Diario!$B$2:$B$229,"<="&D$4) -> 52415.82
A21: TA | B21: TOTAL ACTIVO (A + B) | C21: =C5+C12 -> 75318.61 | D21: =D5+D12 -> 92959.82
B23: PATRIMONIO NETO Y PASIVO | C23: =FechaComparativa -> 46022 | D23: =FechaCorte -> 46287
A24: PA | B24: A) PATRIMONIO NETO | C24: =C25+C26+C27+C28+C29 -> 75318.61 | D24: =D25+D26+D27+D28+D29 -> 67535.82
A25: PAI | B25: I. Capital | C25: =-SUMIFS(Diario!$K$2:$K$229,Diario!$L$2:$L$229,"PAI",Diario!$B$2:$B$229,"<="&C$4) -> 3100 | D25: =-SUMIFS(Diario!$K$2:$K$229,Diario!$L$2:$L$229,"PAI",Diario!$B$2:$B$229,"<="&D$4) -> 3100
A26: PAIII | B26: III. Reservas | C26: =-SUMIFS(Diario!$K$2:$K$229,Diario!$L$2:$L$229,"PAIII",Diario!$B$2:$B$229,"<="&C$4) -> 0 | D26: =-SUMIFS(Diario!$K$2:$K$229,Diario!$L$2:$L$229,"PAIII",Diario!$B$2:$B$229,"<="&D$4) -> 6.49
A27: PAV | B27: V. Resultados de ejercicios anteriores | C27: =-SUMIFS(Diario!$K$2:$K$229,Diario!$L$2:$L$229,"PAV",Diario!$B$2:$B$229,"<="&C$4) -> 0 | D27: =-SUMIFS(Diario!$K$2:$K$229,Diario!$L$2:$L$229,"PAV",Diario!$B$2:$B$229,"<="&D$4) -> 58.39
A28: PAVI | B28: VI. Otras aportaciones de socios | C28: =-SUMIFS(Diario!$K$2:$K$229,Diario!$L$2:$L$229,"PAVI",Diario!$B$2:$B$229,"<="&C$4) -> 72153.73 | D28: =-SUMIFS(Diario!$K$2:$K$229,Diario!$L$2:$L$229,"PAVI",Diario!$B$2:$B$229,"<="&D$4) -> 72153.73
A29: PAVII | B29: VII. Resultado del ejercicio | C29: =-SUMIFS(Diario!$K$2:$K$229,Diario!$L$2:$L$229,"PAVII",Diario!$B$2:$B$229,"<="&C$4) -> 64.88 | D29: =-SUMIFS(Diario!$K$2:$K$229,Diario!$L$2:$L$229,"PAVII",Diario!$B$2:$B$229,"<="&D$4) -> -7782.79
A30: PB | B30: B) PASIVO NO CORRIENTE | C30: =C31 -> 0 | D30: =D31 -> 0
A31: PBII | B31: II. Deudas a largo plazo (bancos, préstamos de socios) | C31: =-SUMIFS(Diario!$K$2:$K$229,Diario!$L$2:$L$229,"PBII",Diario!$B$2:$B$229,"<="&C$4) -> 0 | D31: =-SUMIFS(Diario!$K$2:$K$229,Diario!$L$2:$L$229,"PBII",Diario!$B$2:$B$229,"<="&D$4) -> 0
A32: PC | B32: C) PASIVO CORRIENTE | C32: =C33+C37 -> 0 | D32: =D33+D37 -> 25424
A33: PCIII | B33: III. Deudas a corto plazo | C33: =C34+C35+C36 -> 0 | D33: =D34+D35+D36 -> 24498.06
A34: PCIII1 | B34: 1. Deudas con entidades de crédito | C34: =-SUMIFS(Diario!$K$2:$K$229,Diario!$L$2:$L$229,"PCIII1",Diario!$B$2:$B$229,"<="&C$4) -> 0 | D34: =-SUMIFS(Diario!$K$2:$K$229,Diario!$L$2:$L$229,"PCIII1",Diario!$B$2:$B$229,"<="&D$4) -> 0
A35: PCIII2 | B35: 2. Deudas con socios | C35: =MAX(0,-SUMIFS(Diario!$K$2:$K$229,Diario!$L$2:$L$229,"D551",Diario!$B$2:$B$229,"<="&C$4)) -> 0 | D35: =MAX(0,-SUMIFS(Diario!$K$2:$K$229,Diario!$L$2:$L$229,"D551",Diario!$B$2:$B$229,"<="&D$4)) -> 0
A36: PCIII3 | B36: 3. Partidas pendientes de aplicación (saldo acreedor) | C36: =MAX(0,-SUMIFS(Diario!$K$2:$K$229,Diario!$L$2:$L$229,"D555",Diario!$B$2:$B$229,"<="&C$4)) -> 0 | D36: =MAX(0,-SUMIFS(Diario!$K$2:$K$229,Diario!$L$2:$L$229,"D555",Diario!$B$2:$B$229,"<="&D$4)) -> 24498.06
A37: PCV | B37: V. Acreedores comerciales y otras cuentas a pagar | C37: =C38+C39+C40 -> 0 | D37: =D38+D39+D40 -> 925.94
A38: PCV1 | B38: 1. Proveedores y acreedores | C38: =-SUMIFS(Diario!$K$2:$K$229,Diario!$L$2:$L$229,"PCV1",Diario!$B$2:$B$229,"<="&C$4) -> 0 | D38: =-SUMIFS(Diario!$K$2:$K$229,Diario!$L$2:$L$229,"PCV1",Diario!$B$2:$B$229,"<="&D$4) -> 640.95
A39: PCV2 | B39: 2. Hacienda Pública acreedora (IVA, retenciones, Sociedades) | C39: =-SUMIFS(Diario!$K$2:$K$229,Diario!$L$2:$L$229,"PCV2",Diario!$B$2:$B$229,"<="&C$4) -> 0 | D39: =-SUMIFS(Diario!$K$2:$K$229,Diario!$L$2:$L$229,"PCV2",Diario!$B$2:$B$229,"<="&D$4) -> 284.99
A40: PCV3 | B40: 3. Seguridad Social y personal | C40: =-SUMIFS(Diario!$K$2:$K$229,Diario!$L$2:$L$229,"PCV3",Diario!$B$2:$B$229,"<="&C$4) -> 0 | D40: =-SUMIFS(Diario!$K$2:$K$229,Diario!$L$2:$L$229,"PCV3",Diario!$B$2:$B$229,"<="&D$4) -> 0
A41: TP | B41: TOTAL PATRIMONIO NETO Y PASIVO (A + B + C) | C41: =C24+C30+C32 -> 75318.61 | D41: =D24+D30+D32 -> 92959.82
B43: Comprobación: Activo − (Patrimonio neto + Pasivo) | C43: =C21-C41 -> 0 | D43: =D21-D41 -> 0
B44: Si sale distinto de «-» (cero), algo está mal registrado.

Sheet PyG
A1: Cuenta de Pérdidas y Ganancias - Berts Solutions SL
A2: Modelo PGC Pymes. Ingresos en positivo, gastos entre paréntesis. Trimestres del año de la fecha de corte.
C4: 2025 (Fisama) | D4: ="T1 "&YEAR(FechaCorte) -> T1 2026 | E4: ="T2 "&YEAR(FechaCorte) -> T2 2026 | F4: ="T3 "&YEAR(FechaCorte) -> T3 2026 | G4: ="T4 "&YEAR(FechaCorte) -> T4 2026 | H4: Acumulado a fecha de corte
B5: Desde | C5: 01/01/2025 | D5: =DATE(YEAR(FechaCorte),1,1) -> 46023 | E5: =DATE(YEAR(FechaCorte),4,1) -> 46113 | F5: =DATE(YEAR(FechaCorte),7,1) -> 46204 | G5: =DATE(YEAR(FechaCorte),10,1) -> 46296 | H5: =DATE(YEAR(FechaCorte),1,1) -> 46023
B6: Hasta | C6: 31/12/2025 | D6: =MIN(DATE(YEAR(FechaCorte),4,1)-1,FechaCorte) -> 46112 | E6: =MIN(DATE(YEAR(FechaCorte),7,1)-1,FechaCorte) -> 46203 | F6: =MIN(DATE(YEAR(FechaCorte),10,1)-1,FechaCorte) -> 46287 | G6: =MIN(DATE(YEAR(FechaCorte),13,1)-1,FechaCorte) -> 46287 | H6: =FechaCorte -> 46287
A8: P1 | B8: 1. Importe neto de la cifra de negocios | C8: 2574.25 | D8: =-SUMIFS(Diario!$K$2:$K$229,Diario!$M$2:$M$229,"P1",Diario!$B$2:$B$229,">="&D$5,Diario!$B$2:$B$229,"<="&D$6,Diario!$H$2:$H$229,"<>REG") -> 0 | E8: =-SUMIFS(Diario!$K$2:$K$229,Diario!$M$2:$M$229,"P1",Diario!$B$2:$B$229,">="&E$5,Diario!$B$2:$B$229,"<="&E$6,Diario!$H$2:$H$229,"<>REG") -> 1737.73 | F8: =-SUMIFS(Diario!$K$2:$K$229,Diario!$M$2:$M$229,"P1",Diario!$B$2:$B$229,">="&F$5,Diario!$B$2:$B$229,"<="&F$6,Diario!$H$2:$H$229,"<>REG") -> 0 | G8: =-SUMIFS(Diario!$K$2:$K$229,Diario!$M$2:$M$229,"P1",Diario!$B$2:$B$229,">="&G$5,Diario!$B$2:$B$229,"<="&G$6,Diario!$H$2:$H$229,"<>REG") -> 0 | H8: =-SUMIFS(Diario!$K$2:$K$229,Diario!$M$2:$M$229,"P1",Diario!$B$2:$B$229,">="&H$5,Diario!$B$2:$B$229,"<="&H$6,Diario!$H$2:$H$229,"<>REG") -> 1737.73
A9: P4 | B9: 4. Aprovisionamientos | C9: 0 | D9: =-SUMIFS(Diario!$K$2:$K$229,Diario!$M$2:$M$229,"P4",Diario!$B$2:$B$229,">="&D$5,Diario!$B$2:$B$229,"<="&D$6,Diario!$H$2:$H$229,"<>REG") -> 0 | E9: =-SUMIFS(Diario!$K$2:$K$229,Diario!$M$2:$M$229,"P4",Diario!$B$2:$B$229,">="&E$5,Diario!$B$2:$B$229,"<="&E$6,Diario!$H$2:$H$229,"<>REG") -> 0 | F9: =-SUMIFS(Diario!$K$2:$K$229,Diario!$M$2:$M$229,"P4",Diario!$B$2:$B$229,">="&F$5,Diario!$B$2:$B$229,"<="&F$6,Diario!$H$2:$H$229,"<>REG") -> 0 | G9: =-SUMIFS(Diario!$K$2:$K$229,Diario!$M$2:$M$229,"P4",Diario!$B$2:$B$229,">="&G$5,Diario!$B$2:$B$229,"<="&G$6,Diario!$H$2:$H$229,"<>REG") -> 0 | H9: =-SUMIFS(Diario!$K$2:$K$229,Diario!$M$2:$M$229,"P4",Diario!$B$2:$B$229,">="&H$5,Diario!$B$2:$B$229,"<="&H$6,Diario!$H$2:$H$229,"<>REG") -> 0
A10: P5 | B10: 5. Otros ingresos de explotación | C10: 0 | D10: =-SUMIFS(Diario!$K$2:$K$229,Diario!$M$2:$M$229,"P5",Diario!$B$2:$B$229,">="&D$5,Diario!$B$2:$B$229,"<="&D$6,Diario!$H$2:$H$229,"<>REG") -> 0 | E10: =-SUMIFS(Diario!$K$2:$K$229,Diario!$M$2:$M$229,"P5",Diario!$B$2:$B$229,">="&E$5,Diario!$B$2:$B$229,"<="&E$6,Diario!$H$2:$H$229,"<>REG") -> 0 | F10: =-SUMIFS(Diario!$K$2:$K$229,Diario!$M$2:$M$229,"P5",Diario!$B$2:$B$229,">="&F$5,Diario!$B$2:$B$229,"<="&F$6,Diario!$H$2:$H$229,"<>REG") -> 0 | G10: =-SUMIFS(Diario!$K$2:$K$229,Diario!$M$2:$M$229,"P5",Diario!$B$2:$B$229,">="&G$5,Diario!$B$2:$B$229,"<="&G$6,Diario!$H$2:$H$229,"<>REG") -> 0 | H10: =-SUMIFS(Diario!$K$2:$K$229,Diario!$M$2:$M$229,"P5",Diario!$B$2:$B$229,">="&H$5,Diario!$B$2:$B$229,"<="&H$6,Diario!$H$2:$H$229,"<>REG") -> 0
A11: P6 | B11: 6. Gastos de personal | C11: 0 | D11: =-SUMIFS(Diario!$K$2:$K$229,Diario!$M$2:$M$229,"P6",Diario!$B$2:$B$229,">="&D$5,Diario!$B$2:$B$229,"<="&D$6,Diario!$H$2:$H$229,"<>REG") -> 0 | E11: =-SUMIFS(Diario!$K$2:$K$229,Diario!$M$2:$M$229,"P6",Diario!$B$2:$B$229,">="&E$5,Diario!$B$2:$B$229,"<="&E$6,Diario!$H$2:$H$229,"<>REG") -> 0 | F11: =-SUMIFS(Diario!$K$2:$K$229,Diario!$M$2:$M$229,"P6",Diario!$B$2:$B$229,">="&F$5,Diario!$B$2:$B$229,"<="&F$6,Diario!$H$2:$H$229,"<>REG") -> 0 | G11: =-SUMIFS(Diario!$K$2:$K$229,Diario!$M$2:$M$229,"P6",Diario!$B$2:$B$229,">="&G$5,Diario!$B$2:$B$229,"<="&G$6,Diario!$H$2:$H$229,"<>REG") -> 0 | H11: =-SUMIFS(Diario!$K$2:$K$229,Diario!$M$2:$M$229,"P6",Diario!$B$2:$B$229,">="&H$5,Diario!$B$2:$B$229,"<="&H$6,Diario!$H$2:$H$229,"<>REG") -> 0
A12: P7 | B12: 7. Otros gastos de explotación | C12: =C13+C14+C15 -> -2509.37 | D12: =D13+D14+D15 -> -1605.21 | E12: =E13+E14+E15 -> -878.97 | F12: =F13+F14+F15 -> -1623.17 | G12: =G13+G14+G15 -> 0 | H12: =H13+H14+H15 -> -4107.35
A13: P7a | B13: a) Servicios exteriores | C13: -2509.37 | D13: =-SUMIFS(Diario!$K$2:$K$229,Diario!$M$2:$M$229,"P7a",Diario!$B$2:$B$229,">="&D$5,Diario!$B$2:$B$229,"<="&D$6,Diario!$H$2:$H$229,"<>REG") -> -1605.21 | E13: =-SUMIFS(Diario!$K$2:$K$229,Diario!$M$2:$M$229,"P7a",Diario!$B$2:$B$229,">="&E$5,Diario!$B$2:$B$229,"<="&E$6,Diario!$H$2:$H$229,"<>REG") -> -734.28 | F13: =-SUMIFS(Diario!$K$2:$K$229,Diario!$M$2:$M$229,"P7a",Diario!$B$2:$B$229,">="&F$5,Diario!$B$2:$B$229,"<="&F$6,Diario!$H$2:$H$229,"<>REG") -> -1623.17 | G13: =-SUMIFS(Diario!$K$2:$K$229,Diario!$M$2:$M$229,"P7a",Diario!$B$2:$B$229,">="&G$5,Diario!$B$2:$B$229,"<="&G$6,Diario!$H$2:$H$229,"<>REG") -> 0 | H13: =-SUMIFS(Diario!$K$2:$K$229,Diario!$M$2:$M$229,"P7a",Diario!$B$2:$B$229,">="&H$5,Diario!$B$2:$B$229,"<="&H$6,Diario!$H$2:$H$229,"<>REG") -> -3962.66
A14: P7b | B14: b) Tributos | C14: 0 | D14: =-SUMIFS(Diario!$K$2:$K$229,Diario!$M$2:$M$229,"P7b",Diario!$B$2:$B$229,">="&D$5,Diario!$B$2:$B$229,"<="&D$6,Diario!$H$2:$H$229,"<>REG") -> 0 | E14: =-SUMIFS(Diario!$K$2:$K$229,Diario!$M$2:$M$229,"P7b",Diario!$B$2:$B$229,">="&E$5,Diario!$B$2:$B$229,"<="&E$6,Diario!$H$2:$H$229,"<>REG") -> -144.69 | F14: =-SUMIFS(Diario!$K$2:$K$229,Diario!$M$2:$M$229,"P7b",Diario!$B$2:$B$229,">="&F$5,Diario!$B$2:$B$229,"<="&F$6,Diario!$H$2:$H$229,"<>REG") -> 0 | G14: =-SUMIFS(Diario!$K$2:$K$229,Diario!$M$2:$M$229,"P7b",Diario!$B$2:$B$229,">="&G$5,Diario!$B$2:$B$229,"<="&G$6,Diario!$H$2:$H$229,"<>REG") -> 0 | H14: =-SUMIFS(Diario!$K$2:$K$229,Diario!$M$2:$M$229,"P7b",Diario!$B$2:$B$229,">="&H$5,Diario!$B$2:$B$229,"<="&H$6,Diario!$H$2:$H$229,"<>REG") -> -144.69
A15: P7c | B15: c) Otros gastos de gestión corriente | C15: 0 | D15: =-SUMIFS(Diario!$K$2:$K$229,Diario!$M$2:$M$229,"P7c",Diario!$B$2:$B$229,">="&D$5,Diario!$B$2:$B$229,"<="&D$6,Diario!$H$2:$H$229,"<>REG") -> 0 | E15: =-SUMIFS(Diario!$K$2:$K$229,Diario!$M$2:$M$229,"P7c",Diario!$B$2:$B$229,">="&E$5,Diario!$B$2:$B$229,"<="&E$6,Diario!$H$2:$H$229,"<>REG") -> 0 | F15: =-SUMIFS(Diario!$K$2:$K$229,Diario!$M$2:$M$229,"P7c",Diario!$B$2:$B$229,">="&F$5,Diario!$B$2:$B$229,"<="&F$6,Diario!$H$2:$H$229,"<>REG") -> 0 | G15: =-SUMIFS(Diario!$K$2:$K$229,Diario!$M$2:$M$229,"P7c",Diario!$B$2:$B$229,">="&G$5,Diario!$B$2:$B$229,"<="&G$6,Diario!$H$2:$H$229,"<>REG") -> 0 | H15: =-SUMIFS(Diario!$K$2:$K$229,Diario!$M$2:$M$229,"P7c",Diario!$B$2:$B$229,">="&H$5,Diario!$B$2:$B$229,"<="&H$6,Diario!$H$2:$H$229,"<>REG") -> 0
A16: P8 | B16: 8. Amortización del inmovilizado | C16: 0 | D16: =-SUMIFS(Diario!$K$2:$K$229,Diario!$M$2:$M$229,"P8",Diario!$B$2:$B$229,">="&D$5,Diario!$B$2:$B$229,"<="&D$6,Diario!$H$2:$H$229,"<>REG") -> -498.57 | E16: =-SUMIFS(Diario!$K$2:$K$229,Diario!$M$2:$M$229,"P8",Diario!$B$2:$B$229,">="&E$5,Diario!$B$2:$B$229,"<="&E$6,Diario!$H$2:$H$229,"<>REG") -> -720.29 | F16: =-SUMIFS(Diario!$K$2:$K$229,Diario!$M$2:$M$229,"P8",Diario!$B$2:$B$229,">="&F$5,Diario!$B$2:$B$229,"<="&F$6,Diario!$H$2:$H$229,"<>REG") -> -493.01 | G16: =-SUMIFS(Diario!$K$2:$K$229,Diario!$M$2:$M$229,"P8",Diario!$B$2:$B$229,">="&G$5,Diario!$B$2:$B$229,"<="&G$6,Diario!$H$2:$H$229,"<>REG") -> 0 | H16: =-SUMIFS(Diario!$K$2:$K$229,Diario!$M$2:$M$229,"P8",Diario!$B$2:$B$229,">="&H$5,Diario!$B$2:$B$229,"<="&H$6,Diario!$H$2:$H$229,"<>REG") -> -1711.87
A17: P11 | B17: 11. Deterioro y resultado por enajenaciones del inmovilizado | C17: 0 | D17: =-SUMIFS(Diario!$K$2:$K$229,Diario!$M$2:$M$229,"P11",Diario!$B$2:$B$229,">="&D$5,Diario!$B$2:$B$229,"<="&D$6,Diario!$H$2:$H$229,"<>REG") -> 0 | E17: =-SUMIFS(Diario!$K$2:$K$229,Diario!$M$2:$M$229,"P11",Diario!$B$2:$B$229,">="&E$5,Diario!$B$2:$B$229,"<="&E$6,Diario!$H$2:$H$229,"<>REG") -> -3414.92 | F17: =-SUMIFS(Diario!$K$2:$K$229,Diario!$M$2:$M$229,"P11",Diario!$B$2:$B$229,">="&F$5,Diario!$B$2:$B$229,"<="&F$6,Diario!$H$2:$H$229,"<>REG") -> 0 | G17: =-SUMIFS(Diario!$K$2:$K$229,Diario!$M$2:$M$229,"P11",Diario!$B$2:$B$229,">="&G$5,Diario!$B$2:$B$229,"<="&G$6,Diario!$H$2:$H$229,"<>REG") -> 0 | H17: =-SUMIFS(Diario!$K$2:$K$229,Diario!$M$2:$M$229,"P11",Diario!$B$2:$B$229,">="&H$5,Diario!$B$2:$B$229,"<="&H$6,Diario!$H$2:$H$229,"<>REG") -> -3414.92
A18: P12 | B18: 12. Otros resultados | C18: 0 | D18: =-SUMIFS(Diario!$K$2:$K$229,Diario!$M$2:$M$229,"P12",Diario!$B$2:$B$229,">="&D$5,Diario!$B$2:$B$229,"<="&D$6,Diario!$H$2:$H$229,"<>REG") -> 0 | E18: =-SUMIFS(Diario!$K$2:$K$229,Diario!$M$2:$M$229,"P12",Diario!$B$2:$B$229,">="&E$5,Diario!$B$2:$B$229,"<="&E$6,Diario!$H$2:$H$229,"<>REG") -> 0 | F18: =-SUMIFS(Diario!$K$2:$K$229,Diario!$M$2:$M$229,"P12",Diario!$B$2:$B$229,">="&F$5,Diario!$B$2:$B$229,"<="&F$6,Diario!$H$2:$H$229,"<>REG") -> -286.38 | G18: =-SUMIFS(Diario!$K$2:$K$229,Diario!$M$2:$M$229,"P12",Diario!$B$2:$B$229,">="&G$5,Diario!$B$2:$B$229,"<="&G$6,Diario!$H$2:$H$229,"<>REG") -> 0 | H18: =-SUMIFS(Diario!$K$2:$K$229,Diario!$M$2:$M$229,"P12",Diario!$B$2:$B$229,">="&H$5,Diario!$B$2:$B$229,"<="&H$6,Diario!$H$2:$H$229,"<>REG") -> -286.38
A19: A1 | B19: A.1) RESULTADO DE EXPLOTACIÓN | C19: =C8+C9+C10+C11+C12+C16+C17+C18 -> 64.88 | D19: =D8+D9+D10+D11+D12+D16+D17+D18 -> -2103.78 | E19: =E8+E9+E10+E11+E12+E16+E17+E18 -> -3276.45 | F19: =F8+F9+F10+F11+F12+F16+F17+F18 -> -2402.56 | G19: =G8+G9+G10+G11+G12+G16+G17+G18 -> 0 | H19: =H8+H9+H10+H11+H12+H16+H17+H18 -> -7782.79
A20: P13 | B20: 13. Ingresos financieros | C20: 0 | D20: =-SUMIFS(Diario!$K$2:$K$229,Diario!$M$2:$M$229,"P13",Diario!$B$2:$B$229,">="&D$5,Diario!$B$2:$B$229,"<="&D$6,Diario!$H$2:$H$229,"<>REG") -> 0 | E20: =-SUMIFS(Diario!$K$2:$K$229,Diario!$M$2:$M$229,"P13",Diario!$B$2:$B$229,">="&E$5,Diario!$B$2:$B$229,"<="&E$6,Diario!$H$2:$H$229,"<>REG") -> 0 | F20: =-SUMIFS(Diario!$K$2:$K$229,Diario!$M$2:$M$229,"P13",Diario!$B$2:$B$229,">="&F$5,Diario!$B$2:$B$229,"<="&F$6,Diario!$H$2:$H$229,"<>REG") -> 0 | G20: =-SUMIFS(Diario!$K$2:$K$229,Diario!$M$2:$M$229,"P13",Diario!$B$2:$B$229,">="&G$5,Diario!$B$2:$B$229,"<="&G$6,Diario!$H$2:$H$229,"<>REG") -> 0 | H20: =-SUMIFS(Diario!$K$2:$K$229,Diario!$M$2:$M$229,"P13",Diario!$B$2:$B$229,">="&H$5,Diario!$B$2:$B$229,"<="&H$6,Diario!$H$2:$H$229,"<>REG") -> 0
A21: P14 | B21: 14. Gastos financieros | C21: 0 | D21: =-SUMIFS(Diario!$K$2:$K$229,Diario!$M$2:$M$229,"P14",Diario!$B$2:$B$229,">="&D$5,Diario!$B$2:$B$229,"<="&D$6,Diario!$H$2:$H$229,"<>REG") -> 0 | E21: =-SUMIFS(Diario!$K$2:$K$229,Diario!$M$2:$M$229,"P14",Diario!$B$2:$B$229,">="&E$5,Diario!$B$2:$B$229,"<="&E$6,Diario!$H$2:$H$229,"<>REG") -> 0 | F21: =-SUMIFS(Diario!$K$2:$K$229,Diario!$M$2:$M$229,"P14",Diario!$B$2:$B$229,">="&F$5,Diario!$B$2:$B$229,"<="&F$6,Diario!$H$2:$H$229,"<>REG") -> 0 | G21: =-SUMIFS(Diario!$K$2:$K$229,Diario!$M$2:$M$229,"P14",Diario!$B$2:$B$229,">="&G$5,Diario!$B$2:$B$229,"<="&G$6,Diario!$H$2:$H$229,"<>REG") -> 0 | H21: =-SUMIFS(Diario!$K$2:$K$229,Diario!$M$2:$M$229,"P14",Diario!$B$2:$B$229,">="&H$5,Diario!$B$2:$B$229,"<="&H$6,Diario!$H$2:$H$229,"<>REG") -> 0
A22: P16 | B22: 16. Diferencias de cambio | C22: 0 | D22: =-SUMIFS(Diario!$K$2:$K$229,Diario!$M$2:$M$229,"P16",Diario!$B$2:$B$229,">="&D$5,Diario!$B$2:$B$229,"<="&D$6,Diario!$H$2:$H$229,"<>REG") -> 0 | E22: =-SUMIFS(Diario!$K$2:$K$229,Diario!$M$2:$M$229,"P16",Diario!$B$2:$B$229,">="&E$5,Diario!$B$2:$B$229,"<="&E$6,Diario!$H$2:$H$229,"<>REG") -> 0 | F22: =-SUMIFS(Diario!$K$2:$K$229,Diario!$M$2:$M$229,"P16",Diario!$B$2:$B$229,">="&F$5,Diario!$B$2:$B$229,"<="&F$6,Diario!$H$2:$H$229,"<>REG") -> 0 | G22: =-SUMIFS(Diario!$K$2:$K$229,Diario!$M$2:$M$229,"P16",Diario!$B$2:$B$229,">="&G$5,Diario!$B$2:$B$229,"<="&G$6,Diario!$H$2:$H$229,"<>REG") -> 0 | H22: =-SUMIFS(Diario!$K$2:$K$229,Diario!$M$2:$M$229,"P16",Diario!$B$2:$B$229,">="&H$5,Diario!$B$2:$B$229,"<="&H$6,Diario!$H$2:$H$229,"<>REG") -> 0
A23: A2 | B23: A.2) RESULTADO FINANCIERO | C23: =C20+C21+C22 -> 0 | D23: =D20+D21+D22 -> 0 | E23: =E20+E21+E22 -> 0 | F23: =F20+F21+F22 -> 0 | G23: =G20+G21+G22 -> 0 | H23: =H20+H21+H22 -> 0
A24: A3 | B24: A.3) RESULTADO ANTES DE IMPUESTOS | C24: =C19+C23 -> 64.88 | D24: =D19+D23 -> -2103.78 | E24: =E19+E23 -> -3276.45 | F24: =F19+F23 -> -2402.56 | G24: =G19+G23 -> 0 | H24: =H19+H23 -> -7782.79
A25: P17 | B25: 17. Impuestos sobre beneficios | C25: 0 | D25: =-SUMIFS(Diario!$K$2:$K$229,Diario!$M$2:$M$229,"P17",Diario!$B$2:$B$229,">="&D$5,Diario!$B$2:$B$229,"<="&D$6,Diario!$H$2:$H$229,"<>REG") -> 0 | E25: =-SUMIFS(Diario!$K$2:$K$229,Diario!$M$2:$M$229,"P17",Diario!$B$2:$B$229,">="&E$5,Diario!$B$2:$B$229,"<="&E$6,Diario!$H$2:$H$229,"<>REG") -> 0 | F25: =-SUMIFS(Diario!$K$2:$K$229,Diario!$M$2:$M$229,"P17",Diario!$B$2:$B$229,">="&F$5,Diario!$B$2:$B$229,"<="&F$6,Diario!$H$2:$H$229,"<>REG") -> 0 | G25: =-SUMIFS(Diario!$K$2:$K$229,Diario!$M$2:$M$229,"P17",Diario!$B$2:$B$229,">="&G$5,Diario!$B$2:$B$229,"<="&G$6,Diario!$H$2:$H$229,"<>REG") -> 0 | H25: =-SUMIFS(Diario!$K$2:$K$229,Diario!$M$2:$M$229,"P17",Diario!$B$2:$B$229,">="&H$5,Diario!$B$2:$B$229,"<="&H$6,Diario!$H$2:$H$229,"<>REG") -> 0
A26: A4 | B26: A.4) RESULTADO DEL EJERCICIO | C26: =C24+C25 -> 64.88 | D26: =D24+D25 -> -2103.78 | E26: =E24+E25 -> -3276.45 | F26: =F24+F25 -> -2402.56 | G26: =G24+G25 -> 0 | H26: =H24+H25 -> -7782.79
A29: Cuenta | B29: Detalle por cuenta (ingresos y gastos) | D29: T1 | E29: T2 | F29: T3 | G29: T4 | H29: Acumulado
A30: 6220 | B30: Reparaciones y conservación | D30: =-SUMIFS(Diario!$K$2:$K$229,Diario!$C$2:$C$229,$A30,Diario!$B$2:$B$229,">="&D$5,Diario!$B$2:$B$229,"<="&D$6,Diario!$H$2:$H$229,"<>REG") -> -964.26 | E30: =-SUMIFS(Diario!$K$2:$K$229,Diario!$C$2:$C$229,$A30,Diario!$B$2:$B$229,">="&E$5,Diario!$B$2:$B$229,"<="&E$6,Diario!$H$2:$H$229,"<>REG") -> -351.9 | F30: =-SUMIFS(Diario!$K$2:$K$229,Diario!$C$2:$C$229,$A30,Diario!$B$2:$B$229,">="&F$5,Diario!$B$2:$B$229,"<="&F$6,Diario!$H$2:$H$229,"<>REG") -> -676.17 | G30: =-SUMIFS(Diario!$K$2:$K$229,Diario!$C$2:$C$229,$A30,Diario!$B$2:$B$229,">="&G$5,Diario!$B$2:$B$229,"<="&G$6,Diario!$H$2:$H$229,"<>REG") -> 0 | H30: =-SUMIFS(Diario!$K$2:$K$229,Diario!$C$2:$C$229,$A30,Diario!$B$2:$B$229,">="&H$5,Diario!$B$2:$B$229,"<="&H$6,Diario!$H$2:$H$229,"<>REG") -> -1992.33
A31: 6230 | B31: Servicios de profesionales independientes | D31: =-SUMIFS(Diario!$K$2:$K$229,Diario!$C$2:$C$229,$A31,Diario!$B$2:$B$229,">="&D$5,Diario!$B$2:$B$229,"<="&D$6,Diario!$H$2:$H$229,"<>REG") -> 0 | E31: =-SUMIFS(Diario!$K$2:$K$229,Diario!$C$2:$C$229,$A31,Diario!$B$2:$B$229,">="&E$5,Diario!$B$2:$B$229,"<="&E$6,Diario!$H$2:$H$229,"<>REG") -> -41.49 | F31: =-SUMIFS(Diario!$K$2:$K$229,Diario!$C$2:$C$229,$A31,Diario!$B$2:$B$229,">="&F$5,Diario!$B$2:$B$229,"<="&F$6,Diario!$H$2:$H$229,"<>REG") -> 0 | G31: =-SUMIFS(Diario!$K$2:$K$229,Diario!$C$2:$C$229,$A31,Diario!$B$2:$B$229,">="&G$5,Diario!$B$2:$B$229,"<="&G$6,Diario!$H$2:$H$229,"<>REG") -> 0 | H31: =-SUMIFS(Diario!$K$2:$K$229,Diario!$C$2:$C$229,$A31,Diario!$B$2:$B$229,">="&H$5,Diario!$B$2:$B$229,"<="&H$6,Diario!$H$2:$H$229,"<>REG") -> -41.49
A32: 6250 | B32: Primas de seguros | D32: =-SUMIFS(Diario!$K$2:$K$229,Diario!$C$2:$C$229,$A32,Diario!$B$2:$B$229,">="&D$5,Diario!$B$2:$B$229,"<="&D$6,Diario!$H$2:$H$229,"<>REG") -> -640.95 | E32: =-SUMIFS(Diario!$K$2:$K$229,Diario!$C$2:$C$229,$A32,Diario!$B$2:$B$229,">="&E$5,Diario!$B$2:$B$229,"<="&E$6,Diario!$H$2:$H$229,"<>REG") -> 0 | F32: =-SUMIFS(Diario!$K$2:$K$229,Diario!$C$2:$C$229,$A32,Diario!$B$2:$B$229,">="&F$5,Diario!$B$2:$B$229,"<="&F$6,Diario!$H$2:$H$229,"<>REG") -> 0 | G32: =-SUMIFS(Diario!$K$2:$K$229,Diario!$C$2:$C$229,$A32,Diario!$B$2:$B$229,">="&G$5,Diario!$B$2:$B$229,"<="&G$6,Diario!$H$2:$H$229,"<>REG") -> 0 | H32: =-SUMIFS(Diario!$K$2:$K$229,Diario!$C$2:$C$229,$A32,Diario!$B$2:$B$229,">="&H$5,Diario!$B$2:$B$229,"<="&H$6,Diario!$H$2:$H$229,"<>REG") -> -640.95
A33: 6280 | B33: Suministros (combustible, luz, teléfono...) | D33: =-SUMIFS(Diario!$K$2:$K$229,Diario!$C$2:$C$229,$A33,Diario!$B$2:$B$229,">="&D$5,Diario!$B$2:$B$229,"<="&D$6,Diario!$H$2:$H$229,"<>REG") -> 0 | E33: =-SUMIFS(Diario!$K$2:$K$229,Diario!$C$2:$C$229,$A33,Diario!$B$2:$B$229,">="&E$5,Diario!$B$2:$B$229,"<="&E$6,Diario!$H$2:$H$229,"<>REG") -> -106.53 | F33: =-SUMIFS(Diario!$K$2:$K$229,Diario!$C$2:$C$229,$A33,Diario!$B$2:$B$229,">="&F$5,Diario!$B$2:$B$229,"<="&F$6,Diario!$H$2:$H$229,"<>REG") -> 0 | G33: =-SUMIFS(Diario!$K$2:$K$229,Diario!$C$2:$C$229,$A33,Diario!$B$2:$B$229,">="&G$5,Diario!$B$2:$B$229,"<="&G$6,Diario!$H$2:$H$229,"<>REG") -> 0 | H33: =-SUMIFS(Diario!$K$2:$K$229,Diario!$C$2:$C$229,$A33,Diario!$B$2:$B$229,">="&H$5,Diario!$B$2:$B$229,"<="&H$6,Diario!$H$2:$H$229,"<>REG") -> -106.53
A34: 6290 | B34: Otros servicios | D34: =-SUMIFS(Diario!$K$2:$K$229,Diario!$C$2:$C$229,$A34,Diario!$B$2:$B$229,">="&D$5,Diario!$B$2:$B$229,"<="&D$6,Diario!$H$2:$H$229,"<>REG") -> 0 | E34: =-SUMIFS(Diario!$K$2:$K$229,Diario!$C$2:$C$229,$A34,Diario!$B$2:$B$229,">="&E$5,Diario!$B$2:$B$229,"<="&E$6,Diario!$H$2:$H$229,"<>REG") -> -234.36 | F34: =-SUMIFS(Diario!$K$2:$K$229,Diario!$C$2:$C$229,$A34,Diario!$B$2:$B$229,">="&F$5,Diario!$B$2:$B$229,"<="&F$6,Diario!$H$2:$H$229,"<>REG") -> -947 | G34: =-SUMIFS(Diario!$K$2:$K$229,Diario!$C$2:$C$229,$A34,Diario!$B$2:$B$229,">="&G$5,Diario!$B$2:$B$229,"<="&G$6,Diario!$H$2:$H$229,"<>REG") -> 0 | H34: =-SUMIFS(Diario!$K$2:$K$229,Diario!$C$2:$C$229,$A34,Diario!$B$2:$B$229,">="&H$5,Diario!$B$2:$B$229,"<="&H$6,Diario!$H$2:$H$229,"<>REG") -> -1181.36
A35: 6310 | B35: Otros tributos (IVTM...) | D35: =-SUMIFS(Diario!$K$2:$K$229,Diario!$C$2:$C$229,$A35,Diario!$B$2:$B$229,">="&D$5,Diario!$B$2:$B$229,"<="&D$6,Diario!$H$2:$H$229,"<>REG") -> 0 | E35: =-SUMIFS(Diario!$K$2:$K$229,Diario!$C$2:$C$229,$A35,Diario!$B$2:$B$229,">="&E$5,Diario!$B$2:$B$229,"<="&E$6,Diario!$H$2:$H$229,"<>REG") -> -144.69 | F35: =-SUMIFS(Diario!$K$2:$K$229,Diario!$C$2:$C$229,$A35,Diario!$B$2:$B$229,">="&F$5,Diario!$B$2:$B$229,"<="&F$6,Diario!$H$2:$H$229,"<>REG") -> 0 | G35: =-SUMIFS(Diario!$K$2:$K$229,Diario!$C$2:$C$229,$A35,Diario!$B$2:$B$229,">="&G$5,Diario!$B$2:$B$229,"<="&G$6,Diario!$H$2:$H$229,"<>REG") -> 0 | H35: =-SUMIFS(Diario!$K$2:$K$229,Diario!$C$2:$C$229,$A35,Diario!$B$2:$B$229,">="&H$5,Diario!$B$2:$B$229,"<="&H$6,Diario!$H$2:$H$229,"<>REG") -> -144.69
A36: 6710 | B36: Pérdidas procedentes del inmovilizado material | D36: =-SUMIFS(Diario!$K$2:$K$229,Diario!$C$2:$C$229,$A36,Diario!$B$2:$B$229,">="&D$5,Diario!$B$2:$B$229,"<="&D$6,Diario!$H$2:$H$229,"<>REG") -> 0 | E36: =-SUMIFS(Diario!$K$2:$K$229,Diario!$C$2:$C$229,$A36,Diario!$B$2:$B$229,">="&E$5,Diario!$B$2:$B$229,"<="&E$6,Diario!$H$2:$H$229,"<>REG") -> -3414.92 | F36: =-SUMIFS(Diario!$K$2:$K$229,Diario!$C$2:$C$229,$A36,Diario!$B$2:$B$229,">="&F$5,Diario!$B$2:$B$229,"<="&F$6,Diario!$H$2:$H$229,"<>REG") -> 0 | G36: =-SUMIFS(Diario!$K$2:$K$229,Diario!$C$2:$C$229,$A36,Diario!$B$2:$B$229,">="&G$5,Diario!$B$2:$B$229,"<="&G$6,Diario!$H$2:$H$229,"<>REG") -> 0 | H36: =-SUMIFS(Diario!$K$2:$K$229,Diario!$C$2:$C$229,$A36,Diario!$B$2:$B$229,">="&H$5,Diario!$B$2:$B$229,"<="&H$6,Diario!$H$2:$H$229,"<>REG") -> -3414.92
A37: 6780 | B37: Gastos excepcionales (sanciones...) | D37: =-SUMIFS(Diario!$K$2:$K$229,Diario!$C$2:$C$229,$A37,Diario!$B$2:$B$229,">="&D$5,Diario!$B$2:$B$229,"<="&D$6,Diario!$H$2:$H$229,"<>REG") -> 0 | E37: =-SUMIFS(Diario!$K$2:$K$229,Diario!$C$2:$C$229,$A37,Diario!$B$2:$B$229,">="&E$5,Diario!$B$2:$B$229,"<="&E$6,Diario!$H$2:$H$229,"<>REG") -> 0 | F37: =-SUMIFS(Diario!$K$2:$K$229,Diario!$C$2:$C$229,$A37,Diario!$B$2:$B$229,">="&F$5,Diario!$B$2:$B$229,"<="&F$6,Diario!$H$2:$H$229,"<>REG") -> -286.38 | G37: =-SUMIFS(Diario!$K$2:$K$229,Diario!$C$2:$C$229,$A37,Diario!$B$2:$B$229,">="&G$5,Diario!$B$2:$B$229,"<="&G$6,Diario!$H$2:$H$229,"<>REG") -> 0 | H37: =-SUMIFS(Diario!$K$2:$K$229,Diario!$C$2:$C$229,$A37,Diario!$B$2:$B$229,">="&H$5,Diario!$B$2:$B$229,"<="&H$6,Diario!$H$2:$H$229,"<>REG") -> -286.38
A38: 6810 | B38: Amortización del inmovilizado material | D38: =-SUMIFS(Diario!$K$2:$K$229,Diario!$C$2:$C$229,$A38,Diario!$B$2:$B$229,">="&D$5,Diario!$B$2:$B$229,"<="&D$6,Diario!$H$2:$H$229,"<>REG") -> -498.57 | E38: =-SUMIFS(Diario!$K$2:$K$229,Diario!$C$2:$C$229,$A38,Diario!$B$2:$B$229,">="&E$5,Diario!$B$2:$B$229,"<="&E$6,Diario!$H$2:$H$229,"<>REG") -> -720.29 | F38: =-SUMIFS(Diario!$K$2:$K$229,Diario!$C$2:$C$229,$A38,Diario!$B$2:$B$229,">="&F$5,Diario!$B$2:$B$229,"<="&F$6,Diario!$H$2:$H$229,"<>REG") -> -493.01 | G38: =-SUMIFS(Diario!$K$2:$K$229,Diario!$C$2:$C$229,$A38,Diario!$B$2:$B$229,">="&G$5,Diario!$B$2:$B$229,"<="&G$6,Diario!$H$2:$H$229,"<>REG") -> 0 | H38: =-SUMIFS(Diario!$K$2:$K$229,Diario!$C$2:$C$229,$A38,Diario!$B$2:$B$229,">="&H$5,Diario!$B$2:$B$229,"<="&H$6,Diario!$H$2:$H$229,"<>REG") -> -1711.87
A39: 7050 | B39: Prestaciones de servicios (alquileres) | D39: =-SUMIFS(Diario!$K$2:$K$229,Diario!$C$2:$C$229,$A39,Diario!$B$2:$B$229,">="&D$5,Diario!$B$2:$B$229,"<="&D$6,Diario!$H$2:$H$229,"<>REG") -> 0 | E39: =-SUMIFS(Diario!$K$2:$K$229,Diario!$C$2:$C$229,$A39,Diario!$B$2:$B$229,">="&E$5,Diario!$B$2:$B$229,"<="&E$6,Diario!$H$2:$H$229,"<>REG") -> 1737.73 | F39: =-SUMIFS(Diario!$K$2:$K$229,Diario!$C$2:$C$229,$A39,Diario!$B$2:$B$229,">="&F$5,Diario!$B$2:$B$229,"<="&F$6,Diario!$H$2:$H$229,"<>REG") -> 0 | G39: =-SUMIFS(Diario!$K$2:$K$229,Diario!$C$2:$C$229,$A39,Diario!$B$2:$B$229,">="&G$5,Diario!$B$2:$B$229,"<="&G$6,Diario!$H$2:$H$229,"<>REG") -> 0 | H39: =-SUMIFS(Diario!$K$2:$K$229,Diario!$C$2:$C$229,$A39,Diario!$B$2:$B$229,">="&H$5,Diario!$B$2:$B$229,"<="&H$6,Diario!$H$2:$H$229,"<>REG") -> 1737.73
B40: Total = Resultado del ejercicio | D40: =SUM(D30:D39) -> -2103.78 | E40: =SUM(E30:E39) -> -3276.45 | F40: =SUM(F30:F39) -> -2402.56 | G40: =SUM(G30:G39) -> 0 | H40: =SUM(H30:H39) -> -7782.79

Sheet Vehículos
A1: Inmovilizado: vehículos, amortización y rentabilidad
A2: Coste activado = precio + gastos necesarios para ponerlo a rodar (ITP, gestoría, aduana, matriculación). Amortización lineal por días.
A4: ID | B4: Vehículo | C4: Matrícula | D4: Estado | E4: Precio compra (€) | F4: ¿Precio estimado? | G4: % amort. anual | H4: Coste activado total (€) | I4: Amortización dotada (€) | J4: Valor neto contable (€) | K4: Ingresos (€) | L4: Gastos incl. amortización (€) | M4: Resultado del vehículo (€)
A5: V1 | B5: Nissan NV200 Furgon 1.5 dCi 90cv | C5: 1370KGF | D5: en_alquiler | E5: 3800 | F5: no | G5: 0.16 | H5: =SUMIFS(Diario!$F$2:$F$229,Diario!$I$2:$I$229,$A5,Diario!$C$2:$C$229,"218*",Diario!$B$2:$B$229,"<="&FechaCorte) -> 4197.04 | I5: =SUMIFS(Diario!$K$2:$K$229,Diario!$I$2:$I$229,$A5,Diario!$C$2:$C$229,"681*",Diario!$B$2:$B$229,"<="&FechaCorte) -> 382.31 | J5: =SUMIFS(Diario!$K$2:$K$229,Diario!$I$2:$I$229,$A5,Diario!$C$2:$C$229,"218*",Diario!$B$2:$B$229,"<="&FechaCorte)+SUMIFS(Diario!$K$2:$K$229,Diario!$I$2:$I$229,$A5,Diario!$C$2:$C$229,"281*",Diario!$B$2:$B$229,"<="&FechaCorte) -> 3814.73 | K5: =-SUMIFS(Diario!$K$2:$K$229,Diario!$I$2:$I$229,$A5,Diario!$C$2:$C$229,"7*",Diario!$H$2:$H$229,"<>REG",Diario!$B$2:$B$229,"<="&FechaCorte) -> 175.71 | L5: =SUMIFS(Diario!$K$2:$K$229,Diario!$I$2:$I$229,$A5,Diario!$C$2:$C$229,"6*",Diario!$H$2:$H$229,"<>REG",Diario!$B$2:$B$229,"<="&FechaCorte) -> 1449.43 | M5: =K5-L5 -> -1273.72
A6: V2 | B6: Nissan NV200 Furgon 1.5 dCi 90cv | C6: 2436KSS | D6: en_alquiler | E6: 9192 | F6: si | G6: 0.16 | H6: =SUMIFS(Diario!$F$2:$F$229,Diario!$I$2:$I$229,$A6,Diario!$C$2:$C$229,"218*",Diario!$B$2:$B$229,"<="&FechaCorte) -> 9192 | I6: =SUMIFS(Diario!$K$2:$K$229,Diario!$I$2:$I$229,$A6,Diario!$C$2:$C$229,"681*",Diario!$B$2:$B$229,"<="&FechaCorte) -> 1067.78 | J6: =SUMIFS(Diario!$K$2:$K$229,Diario!$I$2:$I$229,$A6,Diario!$C$2:$C$229,"218*",Diario!$B$2:$B$229,"<="&FechaCorte)+SUMIFS(Diario!$K$2:$K$229,Diario!$I$2:$I$229,$A6,Diario!$C$2:$C$229,"281*",Diario!$B$2:$B$229,"<="&FechaCorte) -> 8124.22 | K6: =-SUMIFS(Diario!$K$2:$K$229,Diario!$I$2:$I$229,$A6,Diario!$C$2:$C$229,"7*",Diario!$H$2:$H$229,"<>REG",Diario!$B$2:$B$229,"<="&FechaCorte) -> 983.51 | L6: =SUMIFS(Diario!$K$2:$K$229,Diario!$I$2:$I$229,$A6,Diario!$C$2:$C$229,"6*",Diario!$H$2:$H$229,"<>REG",Diario!$B$2:$B$229,"<="&FechaCorte) -> 2449.63 | M6: =K6-L6 -> -1466.12
A7: V3 | B7: Ford Fiesta | C7: 4161JHF | D7: vendido | E7: 5800 | F7: no | G7: 0.16 | H7: =SUMIFS(Diario!$F$2:$F$229,Diario!$I$2:$I$229,$A7,Diario!$C$2:$C$229,"218*",Diario!$B$2:$B$229,"<="&FechaCorte) -> 6156.7 | I7: =SUMIFS(Diario!$K$2:$K$229,Diario!$I$2:$I$229,$A7,Diario!$C$2:$C$229,"681*",Diario!$B$2:$B$229,"<="&FechaCorte) -> 261.78 | J7: =SUMIFS(Diario!$K$2:$K$229,Diario!$I$2:$I$229,$A7,Diario!$C$2:$C$229,"218*",Diario!$B$2:$B$229,"<="&FechaCorte)+SUMIFS(Diario!$K$2:$K$229,Diario!$I$2:$I$229,$A7,Diario!$C$2:$C$229,"281*",Diario!$B$2:$B$229,"<="&FechaCorte) -> 0 | K7: =-SUMIFS(Diario!$K$2:$K$229,Diario!$I$2:$I$229,$A7,Diario!$C$2:$C$229,"7*",Diario!$H$2:$H$229,"<>REG",Diario!$B$2:$B$229,"<="&FechaCorte) -> 0 | L7: =SUMIFS(Diario!$K$2:$K$229,Diario!$I$2:$I$229,$A7,Diario!$C$2:$C$229,"6*",Diario!$H$2:$H$229,"<>REG",Diario!$B$2:$B$229,"<="&FechaCorte) -> 3807.86 | M7: =K7-L7 -> -3807.86
A8: V4 | B8: Ford Mustang 2.3L (Blanco) | C8: P7559BDR (temporal) | D8: averiado_motor | E8: 6967.03 | F8: si | G8: 0.16 | H8: =SUMIFS(Diario!$F$2:$F$229,Diario!$I$2:$I$229,$A8,Diario!$C$2:$C$229,"218*",Diario!$B$2:$B$229,"<="&FechaCorte) -> 10475.76 | I8: =SUMIFS(Diario!$K$2:$K$229,Diario!$I$2:$I$229,$A8,Diario!$C$2:$C$229,"681*",Diario!$B$2:$B$229,"<="&FechaCorte) -> 0 | J8: =SUMIFS(Diario!$K$2:$K$229,Diario!$I$2:$I$229,$A8,Diario!$C$2:$C$229,"218*",Diario!$B$2:$B$229,"<="&FechaCorte)+SUMIFS(Diario!$K$2:$K$229,Diario!$I$2:$I$229,$A8,Diario!$C$2:$C$229,"281*",Diario!$B$2:$B$229,"<="&FechaCorte) -> 10475.76 | K8: =-SUMIFS(Diario!$K$2:$K$229,Diario!$I$2:$I$229,$A8,Diario!$C$2:$C$229,"7*",Diario!$H$2:$H$229,"<>REG",Diario!$B$2:$B$229,"<="&FechaCorte) -> 0 | L8: =SUMIFS(Diario!$K$2:$K$229,Diario!$I$2:$I$229,$A8,Diario!$C$2:$C$229,"6*",Diario!$H$2:$H$229,"<>REG",Diario!$B$2:$B$229,"<="&FechaCorte) -> 476.55 | M8: =K8-L8 -> -476.55
A9: V5 | B9: Ford Mustang (Gris) | C9: pendiente | D9: sin_matricular | E9: 7931.03 | F9: si | G9: 0.16 | H9: =SUMIFS(Diario!$F$2:$F$229,Diario!$I$2:$I$229,$A9,Diario!$C$2:$C$229,"218*",Diario!$B$2:$B$229,"<="&FechaCorte) -> 9926.13 | I9: =SUMIFS(Diario!$K$2:$K$229,Diario!$I$2:$I$229,$A9,Diario!$C$2:$C$229,"681*",Diario!$B$2:$B$229,"<="&FechaCorte) -> 0 | J9: =SUMIFS(Diario!$K$2:$K$229,Diario!$I$2:$I$229,$A9,Diario!$C$2:$C$229,"218*",Diario!$B$2:$B$229,"<="&FechaCorte)+SUMIFS(Diario!$K$2:$K$229,Diario!$I$2:$I$229,$A9,Diario!$C$2:$C$229,"281*",Diario!$B$2:$B$229,"<="&FechaCorte) -> 9926.13 | K9: =-SUMIFS(Diario!$K$2:$K$229,Diario!$I$2:$I$229,$A9,Diario!$C$2:$C$229,"7*",Diario!$H$2:$H$229,"<>REG",Diario!$B$2:$B$229,"<="&FechaCorte) -> 0 | L9: =SUMIFS(Diario!$K$2:$K$229,Diario!$I$2:$I$229,$A9,Diario!$C$2:$C$229,"6*",Diario!$H$2:$H$229,"<>REG",Diario!$B$2:$B$229,"<="&FechaCorte) -> 1233.38 | M9: =K9-L9 -> -1233.38
B10: TOTAL | E10: =SUM(E5:E9) -> 33690.06 | H10: =SUM(H5:H9) -> 39947.63 | I10: =SUM(I5:I9) -> 1711.87 | J10: =SUM(J5:J9) -> 32340.84 | K10: =SUM(K5:K9) -> 1159.22 | L10: =SUM(L5:L9) -> 9416.85 | M10: =SUM(M5:M9) -> -8257.63
B12: Gastos sin vehículo asignado (hosting, combustible sin identificar...) no aparecen aquí.
B13: El Ford Fiesta (V3) vendido: su «Gastos» incluye la pérdida contable de la venta.

Sheet IVA
A1: IVA por trimestre (para contrastar con el modelo 303 de Fisama)
A2: Estimación a partir de las facturas registradas. El IVA no deducible (facturas a nombre de otra persona, tickets) no cuenta como soportado.
A4: Trimestre | B4: Desde | C4: Hasta | D4: IVA repercutido (€) | E4: IVA soportado deducible (€) | F4: Diferencia del trimestre (€) | G4: Estado
A5: 2026-T1 | B5: 46023 | C5: 46112 | D5: =-SUMIFS(Diario!$K$2:$K$229,Diario!$C$2:$C$229,"477*",Diario!$B$2:$B$229,">="&B5,Diario!$B$2:$B$229,"<="&C5,Diario!$H$2:$H$229,"<>IVA") -> 0 | E5: =SUMIFS(Diario!$K$2:$K$229,Diario!$C$2:$C$229,"472*",Diario!$B$2:$B$229,">="&B5,Diario!$B$2:$B$229,"<="&C5,Diario!$H$2:$H$229,"<>IVA") -> 236.54 | F5: =D5-E5 -> -236.54 | G5: Cerrado. 236,54 € a compensar en trimestres siguientes
A6: 2026-T2 | B6: 46113 | C6: 46203 | D6: =-SUMIFS(Diario!$K$2:$K$229,Diario!$C$2:$C$229,"477*",Diario!$B$2:$B$229,">="&B6,Diario!$B$2:$B$229,"<="&C6,Diario!$H$2:$H$229,"<>IVA") -> 885.72 | E6: =SUMIFS(Diario!$K$2:$K$229,Diario!$C$2:$C$229,"472*",Diario!$B$2:$B$229,">="&B6,Diario!$B$2:$B$229,"<="&C6,Diario!$H$2:$H$229,"<>IVA") -> 371.69 | F6: =D6-E6 -> 514.03 | G6: Cerrado. Tras compensar 236,54 € de trimestres anteriores: 277,49 € A INGRESAR
A7: 2026-T3 | B7: 46204 | C7: 46295 | D7: =-SUMIFS(Diario!$K$2:$K$229,Diario!$C$2:$C$229,"477*",Diario!$B$2:$B$229,">="&B7,Diario!$B$2:$B$229,"<="&C7,Diario!$H$2:$H$229,"<>IVA") -> 0 | E7: =SUMIFS(Diario!$K$2:$K$229,Diario!$C$2:$C$229,"472*",Diario!$B$2:$B$229,">="&B7,Diario!$B$2:$B$229,"<="&C7,Diario!$H$2:$H$229,"<>IVA") -> 3312.31 | F7: =D7-E7 -> -3312.31 | G7: En curso
A8: 2026-T4 | B8: 46296 | C8: 46387 | D8: =-SUMIFS(Diario!$K$2:$K$229,Diario!$C$2:$C$229,"477*",Diario!$B$2:$B$229,">="&B8,Diario!$B$2:$B$229,"<="&C8,Diario!$H$2:$H$229,"<>IVA") -> 0 | E8: =SUMIFS(Diario!$K$2:$K$229,Diario!$C$2:$C$229,"472*",Diario!$B$2:$B$229,">="&B8,Diario!$B$2:$B$229,"<="&C8,Diario!$H$2:$H$229,"<>IVA") -> 0 | F8: =D8-E8 -> 0 | G8: -
A9: TOTAL | D9: =SUM(D5:D8) -> 885.72 | E9: =SUM(E5:E8) -> 3920.54 | F9: =SUM(F5:F8) -> -3034.82

Sheet Pendiente
A1: Qué falta o no cuadra
A2: Se genera solo cada vez que se actualizan los datos. Cuando nos paséis la información, el aviso desaparece.
A4: Prioridad | B4: Tema | C4: Detalle
A5: ALTA | B5: Cobros pendientes de confirmar | C5: Factura 9 Cielo Elizabeth Castillo Gomez (700,00 €): no sabemos si se ha cobrado. Figura como deuda del cliente.
A6: ALTA | B6: Cobros pendientes de confirmar | C6: Factura 10 David Chaves Jodar (700,00 €): no sabemos si se ha cobrado. Figura como deuda del cliente.
A7: ALTA | B7: Cobros pendientes de confirmar | C7: Factura 12 Cielo Elizabeth Castillo Gomez (490,05 €): no sabemos si se ha cobrado. Figura como deuda del cliente.
A8: ALTA | B8: Cobros pendientes de confirmar | C8: Factura 11 Adrian Diaz-Maroto Hernando (3.000,80 €): no sabemos si se ha cobrado. Figura como deuda del cliente.
A9: ALTA | B9: Cuadre bancario | C9: No tenemos ningún saldo real del BBVA de 2026. Sin extractos no se puede comprobar que la tesorería del balance sea la real.
A10: ALTA | B10: Partidas pendientes de aplicación | C10: Hay 24.498,06 € en la cuenta 555: pagos cuyo origen no sabemos (sobre todo compras de vehículos). Con los extractos del BBVA se reparten entre banco, deuda con socios o aportación.
A11: ALTA | B11: Vehículo V1 | C11: Nissan NV200 Furgon 1.5 dCi 90cv (3.800,00 €): no sabemos desde dónde se pagó (¿BBVA de la empresa? ¿un socio de su bolsillo?). Queda en 'partidas pendientes de aplicación'.
A12: ALTA | B12: Vehículo V3 | C12: Ford Fiesta (5.800,00 €): no sabemos desde dónde se pagó (¿BBVA de la empresa? ¿un socio de su bolsillo?). Queda en 'partidas pendientes de aplicación'.
A13: ALTA | B13: Vehículo V4 | C13: Ford Mustang 2.3L (Blanco): el precio de compra (6.967,03 €) es una ESTIMACIÓN (valor declarado en aduana). Falta la factura de compra real.
A14: ALTA | B14: Vehículo V4 | C14: Ford Mustang 2.3L (Blanco) (6.967,03 €): no sabemos desde dónde se pagó (¿BBVA de la empresa? ¿un socio de su bolsillo?). Queda en 'partidas pendientes de aplicación'.
A15: ALTA | B15: Vehículo V5 | C15: Ford Mustang (Gris): el precio de compra (7.931,03 €) es una ESTIMACIÓN (valor declarado en aduana). Falta la factura de compra real.
... A23: BAJA | B23: Factura emitida | C23: Factura 10 David Chaves Jodar: no sabemos a qué vehículo corresponde (afecta solo a la rentabilidad por vehículo).

Sheet Diario
A1: Asiento | B1: Fecha | C1: Cuenta | D1: Nombre de la cuenta | E1: Concepto | F1: Debe (€) | G1: Haber (€) | H1: Tipo | I1: Vehículo | J1: Documento | K1: Saldo D−H (€) | L1: Línea balance | M1: Línea PyG
A2: 1 | B2: 46022 | C2: 2130 | D2: Maquinaria | E2: Saldo de apertura: Maquinaria | F2: 9192 | H2: APE | J2: Balance 2025 Fisama | K2: =F2-G2 -> 9192 | L2: =INDEX('Plan de cuentas'!$C$5:$C$55,MATCH(C2,'Plan de cuentas'!$A$5:$A$55,0)) -> AII2 | M2: =INDEX('Plan de cuentas'!$D$5:$D$55,MATCH(C2,'Plan de cuentas'!$A$5:$A$55,0)) -> -
A3: 1 | B3: 46022 | C3: 5720 | D3: Bancos c/c BBVA | E3: Saldo de apertura: Bancos c/c BBVA ES73 0182 2458 1902 0130 3686 | F3: 66126.61 | H3: APE | J3: Balance 2025 Fisama | K3: =F3-G3 -> 66126.61 | L3: =INDEX('Plan de cuentas'!$C$5:$C$55,MATCH(C3,'Plan de cuentas'!$A$5:$A$55,0)) -> BVII | M3: =INDEX('Plan de cuentas'!$D$5:$D$55,MATCH(C3,'Plan de cuentas'!$A$5:$A$55,0)) -> -
A4: 1 | B4: 46022 | C4: 1000 | D4: Capital social | E4: Saldo de apertura: Capital social | G4: 3100 | H4: APE | J4: Balance 2025 Fisama | K4: =F4-G4 -> -3100 | L4: =INDEX('Plan de cuentas'!$C$5:$C$55,MATCH(C4,'Plan de cuentas'!$A$5:$A$55,0)) -> PAI | M4: =INDEX('Plan de cuentas'!$D$5:$D$55,MATCH(C4,'Plan de cuentas'!$A$5:$A$55,0)) -> -
A5: 1 | B5: 46022 | C5: 1180 | D5: Aportaciones de socios o propietarios | E5: Saldo de apertura: Aportaciones de socios o propietarios | G5: 72153.73 | H5: APE | J5: Balance 2025 Fisama | K5: =F5-G5 -> -72153.73 | L5: =INDEX('Plan de cuentas'!$C$5:$C$55,MATCH(C5,'Plan de cuentas'!$A$5:$A$55,0)) -> PAVI | M5: =INDEX('Plan de cuentas'!$D$5:$D$55,MATCH(C5,'Plan de cuentas'!$A$5:$A$55,0)) -> -
A6: 1 | B6: 46022 | C6: 1290 | D6: Resultado del ejercicio | E6: Saldo de apertura: Resultado del ejercicio 2025 | G6: 64.88 | H6: APE | J6: Balance 2025 Fisama | K6: =F6-G6 -> -64.88 | L6: =INDEX('Plan de cuentas'!$C$5:$C$55,MATCH(C6,'Plan de cuentas'!$A$5:$A$55,0)) -> PAVII | M6: =INDEX('Plan de cuentas'!$D$5:$D$55,MATCH(C6,'Plan de cuentas'!$A$5:$A$55,0)) -> -
A7: 2 | B7: 46023 | C7: 1290 | D7: Resultado del ejercicio | E7: Aplicacion del resultado 2025 | F7: 64.88 | H7: MAN | J7: M001 documentos/cuentas_anuales/2025_Cuenta-perdidas-y-ganancias-Fisama.pdf | K7: =F7-G7 -> 64.88 | L7: =INDEX('Plan de cuentas'!$C$5:$C$55,MATCH(C7,'Plan de cuentas'!$A$5:$A$55,0)) -> PAVII | M7: =INDEX('Plan de cuentas'!$D$5:$D$55,MATCH(C7,'Plan de cuentas'!$A$5:$A$55,0)) -> -
A8: 2 | B8: 46023 | C8: 1120 | D8: Reserva legal | E8: Aplicacion del resultado 2025 - reserva legal 10% | G8: 6.49 | H8: MAN | J8: M001 documentos/cuentas_anuales/2025_Cuenta-perdidas-y-ganancias-Fisama.pdf | K8: =F8-G8 -> -6.49 | L8: =INDEX('Plan de cuentas'!$C$5:$C$55,MATCH(C8,'Plan de cuentas'!$A$5:$A$55,0)) -> PAIII | M8: =INDEX('Plan de cuentas'!$D$5:$D$55,MATCH(C8,'Plan de cuentas'!$A$5:$A$55,0)) -> -
A9: 2 | B9: 46023 | C9: 1200 | D9: Remanente | E9: Aplicacion del resultado 2025 - remanente | G9: 58.39 | H9: MAN | J9: M001 documentos/cuentas_anuales/2025_Cuenta-perdidas-y-ganancias-Fisama.pdf | K9: =F9-G9 -> -58.39 | L9: =INDEX('Plan de cuentas'!$C$5:$C$55,MATCH(C9,'Plan de cuentas'!$A$5:$A$55,0)) -> PAV | M9: =INDEX('Plan de cuentas'!$D$5:$D$55,MATCH(C9,'Plan de cuentas'!$A$5:$A$55,0)) -> -
A10: 3 | B10: 46023 | C10: 2180 | D10: Elementos de transporte | E10: Reclasificacion NV200 2436KSS de Maquinaria (2130) a Elementos de transporte (2180) | F10: 9192 | H10: MAN | I10: V2 | J10: M002 documentos/cuentas_anuales/2025_Balance-situacion-Fisama.pdf | K10: =F10-G10 -> 9192 | L10: =INDEX('Plan de cuentas'!$C$5:$C$55,MATCH(C10,'Plan de cuentas'!$A$5:$A$55,0)) -> AII1 | M10: =INDEX('Plan de cuentas'!$D$5:$D$55,MATCH(C10,'Plan de cuentas'!$A$5:$A$55,0)) -> -
A11: 3 | B11: 46023 | C11: 2130 | D11: Maquinaria | E11: Reclasificacion NV200 2436KSS de Maquinaria (2130) a Elementos de transporte (2180) | G11: 9192 | H11: MAN | I11: V2 | J11: M002 documentos/cuentas_anuales/2025_Balance-situacion-Fisama.pdf | K11: =F11-G11 -> -9192 | L11: =INDEX('Plan de cuentas'!$C$5:$C$55,MATCH(C11,'Plan de cuentas'!$A$5:$A$55,0)) -> AII2 | M11: =INDEX('Plan de cuentas'!$D$5:$D$55,MATCH(C11,'Plan de cuentas'!$A$5:$A$55,0)) -> -
A12: 4 | B12: 46023 | C12: 6250 | D12: Primas de seguros | E12: Seguro terceros NV200 1370KGF (23/10/2025-23/10/2026) (Mutua Madrilena) | F12: 349.46 | H12: FRR | I12: V1 | J12: MUTUA-12692715 Mutua Madrilena | K12: =F12-G12 -> 349.46 | L12: =INDEX('Plan de cuentas'!$C$5:$C$55,MATCH(C12,'Plan de cuentas'!$A$5:$A$55,0)) -> PAVII | M12: =INDEX('Plan de cuentas'!$D$5:$D$55,MATCH(C12,'Plan de cuentas'!$A$5:$A$55,0)) -> P7a
A13: 4 | B13: 46023 | C13: 4100 | D13: Acreedores por prestaciones de servicios | E13: Seguro terceros NV200 1370KGF (23/10/2025-23/10/2026) (Mutua Madrilena) | G13: 349.46 | H13: FRR | I13: V1 | J13: MUTUA-12692715 Mutua Madrilena | K13: =F13-G13 -> -349.46 | L13: =INDEX('Plan de cuentas'!$C$5:$C$55,MATCH(C13,'Plan de cuentas'!$A$5:$A$55,0)) -> PCV1 | M13: =INDEX('Plan de cuentas'!$D$5:$D$55,MATCH(C13,'Plan de cuentas'!$A$5:$A$55,0)) -> -
A14: 5 | B14: 46023 | C14: 6250 | D14: Primas de seguros | E14: Seguro todo riesgo NV200 2436KSS (09/12/2025-23/10/2026) (Mutua Madrilena) | F14: 291.49 | H14: FRR | I14: V2 | J14: MUTUA-12692873 Mutua Madrilena | K14: =F14-G14 -> 291.49 | L14: =INDEX('Plan de cuentas'!$C$5:$C$55,MATCH(C14,'Plan de cuentas'!$A$5:$A$55,0)) -> PAVII | M14: =INDEX('Plan de cuentas'!$D$5:$D$55,MATCH(C14,'Plan de cuentas'!$A$5:$A$55,0)) -> P7a
A15: 5 | B15: 46023 | C15: 4100 | D15: Acreedores por prestaciones de servicios | E15: Seguro todo riesgo NV200 2436KSS (09/12/2025-23/10/2026) (Mutua Madrilena) | G15: 291.49 | H15: FRR | I15: V2 | J15: MUTUA-12692873 Mutua Madrilena | K15: =F15-G15 -> -291.49 | L15: =INDEX('Plan de cuentas'!$C$5:$C$55,MATCH(C15,'Plan de cuentas'!$A$5:$A$55,0)) -> PCV1 | M15: =INDEX('Plan de cuentas'!$D$5:$D$55,MATCH(C15,'Plan de cuentas'!$A$5:$A$55,0)) -> -
A16: 6 | B16: 46053 | C16: 6810 | D16: Amortización del inmovilizado material | E16: Amortización Nissan NV200 Furgon 1.5 dCi 90cv 2436KSS (31 días al 16% anual) | F16: 124.91 | H16: AMO | I16: V2 | J16: Amortización V2 01/2026 | K16: =F16-G16 -> 124.91 | L16: =INDEX('Plan de cuentas'!$C$5:$C$55,MATCH(C16,'Plan de cuentas'!$A$5:$A$55,0)) -> PAVII | M16: =INDEX('Plan de cuentas'!$D$5:$D$55,MATCH(C16,'Plan de cuentas'!$A$5:$A$55,0)) -> P8
A17: 6 | B17: 46053 | C17: 2818 | D17: Amortización acumulada de elementos de transporte | E17: Amortización Nissan NV200 Furgon 1.5 dCi 90cv 2436KSS (31 días al 16% anual) | G17: 124.91 | H17: AMO | I17: V2 | J17: Amortización V2 01/2026 | K17: =F17-G17 -> -124.91 | L17: =INDEX('Plan de cuentas'!$C$5:$C$55,MATCH(C17,'Plan de cuentas'!$A$5:$A$55,0)) -> AII3 | M17: =INDEX('Plan de cuentas'!$D$5:$D$55,MATCH(C17,'Plan de cuentas'!$A$5:$A$55,0)) -> -
A18: 7 | B18: 46080 | C18: 2180 | D18: Elementos de transporte | E18: Compra Nissan NV200 Furgon 1.5 dCi 90cv 1370KGF a Roberto de Roa (socio) | F18: 3800 | H18: COM | I18: V1 | J18: documentos/vehiculos/V1_1370KGF_2026-02-27_Contrato-compraventa-a-Roberto-de-Roa.pdf | K18: =F18-G18 -> 3800 | L18: =INDEX('Plan de cuentas'!$C$5:$C$55,MATCH(C18,'Plan de cuentas'!$A$5:$A$55,0)) -> AII1 | M18: =INDEX('Plan de cuentas'!$D$5:$D$55,MATCH(C18,'Plan de cuentas'!$A$5:$A$55,0)) -> -
A19: 7 | B19: 46080 | C19: 5550 | D19: Partidas pendientes de aplicación | E19: Compra Nissan NV200 Furgon 1.5 dCi 90cv 1370KGF a Roberto de Roa (socio) | G19: 3800 | H19: COM | I19: V1 | J19: documentos/vehiculos/V1_1370KGF_2026-02-27_Contrato-compraventa-a-Roberto-de-Roa.pdf | K19: =F19-G19 -> -3800 | L19: =INDEX('Plan de cuentas'!$C$5:$C$55,MATCH(C19,'Plan de cuentas'!$A$5:$A$55,0)) -> D555 | M19: =INDEX('Plan de cuentas'!$D$5:$D$55,MATCH(C19,'Plan de cuentas'!$A$5:$A$55,0)) -> -
A20: 8 | B20: 46081 | C20: 6810 | D20: Amortización del inmovilizado material | E20: Amortización Nissan NV200 Furgon 1.5 dCi 90cv 1370KGF (2 días al 16% anual) | F20: 3.33 | H20: AMO | I20: V1 | J20: Amortización V1 02/2026 | K20: =F20-G20 -> 3.33 | L20: =INDEX('Plan de cuentas'!$C$5:$C$55,MATCH(C20,'Plan de cuentas'!$A$5:$A$55,0)) -> PAVII | M20: =INDEX('Plan de cuentas'!$D$5:$D$55,MATCH(C20,'Plan de cuentas'!$A$5:$A$55,0)) -> P8
A21: 8 | B21: 46081 | C21: 2818 | D21: Amortización acumulada de elementos de transporte | E21: Amortización Nissan NV200 Furgon 1.5 dCi 90cv 1370KGF (2 días al 16% anual) | G21: 3.33 | H21: AMO | I21: V1 | J21: Amortización V1 02/2026 | K21: =F21-G21 -> -3.33 | L21: =INDEX('Plan de cuentas'!$C$5:$C$55,MATCH(C21,'Plan de cuentas'!$A$5:$A$55,0)) -> AII3 | M21: =INDEX('Plan de cuentas'!$D$5:$D$55,MATCH(C21,'Plan de cuentas'!$A$5:$A$55,0)) -> -
A22: 9 | B22: 46081 | C22: 6810 | D22: Amortización del inmovilizado material | E22: Amortización Nissan NV200 Furgon 1.5 dCi 90cv 2436KSS (28 días al 16% anual) | F22: 112.82 | H22: AMO | I22: V2 | J22: Amortización V2 02/2026 | K22: =F22-G22 -> 112.82 | L22: =INDEX('Plan de cuentas'!$C$5:$C$55,MATCH(C22,'Plan de cuentas'!$A$5:$A$55,0)) -> PAVII | M22: =INDEX('Plan de cuentas'!$D$5:$D$55,MATCH(C22,'Plan de cuentas'!$A$5:$A$55,0)) -> P8
A23: 9 | B23: 46081 | C23: 2818 | D23: Amortización acumulada de elementos de transporte | E23: Amortización Nissan NV200 Furgon 1.5 dCi 90cv 2436KSS (28 días al 16% anual) | G23: 112.82 | H23: AMO | I23: V2 | J23: Amortización V2 02/2026 | K23: =F23-G23 -> -112.82 | L23: =INDEX('Plan de cuentas'!$C$5:$C$55,MATCH(C23,'Plan de cuentas'!$A$5:$A$55,0)) -> AII3 | M23: =INDEX('Plan de cuentas'!$D$5:$D$55,MATCH(C23,'Plan de cuentas'!$A$5:$A$55,0)) -> -
A24: 10 | B24: 46084 | C24: 6220 | D24: Reparaciones y conservación | E24: Mantenimiento completo NV200 2436KSS: aceite filtros frenos 4 neumaticos alineacion (Taller Carlos Valin SL) | F24: 964.26 | H24: FRR | I24: V2 | J24: 71/2026 Taller Carlos Valin SL | K24: =F24-G24 -> 964.26 | L24: =INDEX('Plan de cuentas'!$C$5:$C$55,MATCH(C24,'Plan de cuentas'!$A$5:$A$55,0)) -> PAVII | M24: =INDEX('Plan de cuentas'!$D$5:$D$55,MATCH(C24,'Plan de cuentas'!$A$5:$A$55,0)) -> P7a
A25: 10 | B25: 46084 | C25: 4720 | D25: H.P. IVA soportado | E25: IVA soportado 71/2026 Taller Carlos Valin SL | F25: 202.52 | H25: FRR | I25: V2 | J25: 71/2026 Taller Carlos Valin SL | K25: =F25-G25 -> 202.52 | L25: =INDEX('Plan de cuentas'!$C$5:$C$55,MATCH(C25,'Plan de cuentas'!$A$5:$A$55,0)) -> BIII2 | M25: =INDEX('Plan de cuentas'!$D$5:$D$55,MATCH(C25,'Plan de cuentas'!$A$5:$A$55,0)) -> -
A26: 10 | B26: 46084 | C26: 4100 | D26: Acreedores por prestaciones de servicios | E26: Mantenimiento completo NV200 2436KSS: aceite filtros frenos 4 neumaticos alineacion (Taller Carlos Valin SL) | G26: 1166.78 | H26: FRR | I26: V2 | J26: 71/2026 Taller Carlos Valin SL | K26: =F26-G26 -> -1166.78 | L26: =INDEX('Plan de cuentas'!$C$5:$C$55,MATCH(C26,'Plan de cuentas'!$A$5:$A$55,0)) -> PCV1 | M26: =INDEX('Plan de cuentas'!$D$5:$D$55,MATCH(C26,'Plan de cuentas'!$A$5:$A$55,0)) -> -
A27: 11 | B27: 46085 | C27: 2180 | D27: Elementos de transporte | E27: Compra Ford Fiesta 4161JHF a Ruth Serrano | F27: 5800 | H27: COM | I27: V3 | J27: documentos/vehiculos/V3_4161JHF_2026-03-04_Contrato-compraventa-Ford-Fiesta.pdf | K27: =F27-G27 -> 5800 | L27: =INDEX('Plan de cuentas'!$C$5:$C$55,MATCH(C27,'Plan de cuentas'!$A$5:$A$55,0)) -> AII1 | M27: =INDEX('Plan de cuentas'!$D$5:$D$55,MATCH(C27,'Plan de cuentas'!$A$5:$A$55,0)) -> -
A28: 11 | B28: 46085 | C28: 5550 | D28: Partidas pendientes de aplicación | E28: Compra Ford Fiesta 4161JHF a Ruth Serrano | G28: 5800 | H28: COM | I28: V3 | J28: documentos/vehiculos/V3_4161JHF_2026-03-04_Contrato-compraventa-Ford-Fiesta.pdf | K28: =F28-G28 -> -5800 | L28: =INDEX('Plan de cuentas'!$C$5:$C$55,MATCH(C28,'Plan de cuentas'!$A$5:$A$55,0)) -> D555 | M28: =INDEX('Plan de cuentas'!$D$5:$D$55,MATCH(C28,'Plan de cuentas'!$A$5:$A$55,0)) -> -
A29: 12 | B29: 46085 | C29: 4100 | D29: Acreedores por prestaciones de servicios | E29: Pago 71/2026 Taller Carlos Valin SL | F29: 1166.78 | H29: PAG | I29: V2 | J29: 71/2026 Taller Carlos Valin SL | K29: =F29-G29 -> 1166.78 | L29: =INDEX('Plan de cuentas'!$C$5:$C$55,MATCH(C29,'Plan de cuentas'!$A$5:$A$55,0)) -> PCV1 | M29: =INDEX('Plan de cuentas'!$D$5:$D$55,MATCH(C29,'Plan de cuentas'!$A$5:$A$55,0)) -> -
A30: 12 | B30: 46085 | C30: 5720 | D30: Bancos c/c BBVA | E30: Pago 71/2026 Taller Carlos Valin SL | G30: 1166.78 | H30: PAG | I30: V2 | J30: 71/2026 Taller Carlos Valin SL | K30: =F30-G30 -> -1166.78 | L30: =INDEX('Plan de cuentas'!$C$5:$C$55,MATCH(C30,'Plan de cuentas'!$A$5:$A$55,0)) -> BVII | M30: =INDEX('Plan de cuentas'!$D$5:$D$55,MATCH(C30,'Plan de cuentas'!$A$5:$A$55,0)) -> -
A31: 13 | B31: 46108 | C31: 2180 | D31: Elementos de transporte | E31: Cambio titularidad Ford Fiesta 4161JHF (suplidos: ITP 232.00 + tasa DGT 55.70 + varios 15.00) (Gestoria Amengual (Miguel Mas Amengual)) | F31: 54 | H31: FRR | I31: V3 | J31: 26A900069 Gestoria Amengual (Miguel Mas Amengual) | K31: =F31-G31 -> 54 | L31: =INDEX('Plan de cuentas'!$C$5:$C$55,MATCH(C31,'Plan de cuentas'!$A$5:$A$55,0)) -> AII1 | M31: =INDEX('Plan de cuentas'!$D$5:$D$55,MATCH(C31,'Plan de cuentas'!$A$5:$A$55,0)) -> -
A32: 13 | B32: 46108 | C32: 4720 | D32: H.P. IVA soportado | E32: IVA soportado 26A900069 Gestoria Amengual (Miguel Mas Amengual) | F32: 11.34 | H32: FRR | I32: V3 | J32: 26A900069 Gestoria Amengual (Miguel Mas Amengual) | K32: =F32-G32 -> 11.34 | L32: =INDEX('Plan de cuentas'!$C$5:$C$55,MATCH(C32,'Plan de cuentas'!$A$5:$A$55,0)) -> BIII2 | M32: =INDEX('Plan de cuentas'!$D$5:$D$55,MATCH(C32,'Plan de cuentas'!$A$5:$A$55,0)) -> -
A33: 13 | B33: 46108 | C33: 2180 | D33: Elementos de transporte | E33: Suplidos: Cambio titularidad Ford Fiesta 4161JHF (suplidos: ITP 232.00 + tasa DGT 55.70 + varios 15.00) (Gestoria Amengual (Miguel Mas Amengual)) | F33: 302.7 | H33: FRR | I33: V3 | J33: 26A900069 Gestoria Amengual (Miguel Mas Amengual) | K33: =F33-G33 -> 302.7 | L33: =INDEX('Plan de cuentas'!$C$5:$C$55,MATCH(C33,'Plan de cuentas'!$A$5:$A$55,0)) -> AII1 | M33: =INDEX('Plan de cuentas'!$D$5:$D$55,MATCH(C33,'Plan de cuentas'!$A$5:$A$55,0)) -> -
A34: 13 | B34: 46108 | C34: 4100 | D34: Acreedores por prestaciones de servicios | E34: Cambio titularidad Ford Fiesta 4161JHF (suplidos: ITP 232.00 + tasa DGT 55.70 + varios 15.00) (Gestoria Amengual (Miguel Mas Amengual)) | G34: 368.04 | H34: FRR | I34: V3 | J34: 26A900069 Gestoria Amengual (Miguel Mas Amengual) | K34: =F34-G34 -> -368.04 | L34: =INDEX('Plan de cuentas'!$C$5:$C$55,MATCH(C34,'Plan de cuentas'!$A$5:$A$55,0)) -> PCV1 | M34: =INDEX('Plan de cuentas'!$D$5:$D$55,MATCH(C34,'Plan de cuentas'!$A$5:$A$55,0)) -> -
A35: 14 | B35: 46108 | C35: 2180 | D35: Elementos de transporte | E35: Cambio titularidad NV200 1370KGF - expediente a nombre de Roberto de Roa (Gestoria Amengual (Miguel Mas Amengual)) | F35: 54 | H35: FRR | I35: V1 | J35: 26A900070 Gestoria Amengual (Miguel Mas Amengual) | K35: =F35-G35 -> 54 | L35: =INDEX('Plan de cuentas'!$C$5:$C$55,MATCH(C35,'Plan de cuentas'!$A$5:$A$55,0)) -> AII1 | M35: =INDEX('Plan de cuentas'!$D$5:$D$55,MATCH(C35,'Plan de cuentas'!$A$5:$A$55,0)) -> -
A36: 14 | B36: 46108 | C36: 4720 | D36: H.P. IVA soportado | E36: IVA soportado 26A900070 Gestoria Amengual (Miguel Mas Amengual) | F36: 11.34 | H36: FRR | I36: V1 | J36: 26A900070 Gestoria Amengual (Miguel Mas Amengual) | K36: =F36-G36 -> 11.34 | L36: =INDEX('Plan de cuentas'!$C$5:$C$55,MATCH(C36,'Plan de cuentas'!$A$5:$A$55,0)) -> BIII2 | M36: =INDEX('Plan de cuentas'!$D$5:$D$55,MATCH(C36,'Plan de cuentas'!$A$5:$A$55,0)) -> -
A37: 14 | B37: 46108 | C37: 2180 | D37: Elementos de transporte | E37: Suplidos: Cambio titularidad NV200 1370KGF - expediente a nombre de Roberto de Roa (Gestoria Amengual (Miguel Mas Amengual)) | F37: 65.7 | H37: FRR | I37: V1 | J37: 26A900070 Gestoria Amengual (Miguel Mas Amengual) | K37: =F37-G37 -> 65.7 | L37: =INDEX('Plan de cuentas'!$C$5:$C$55,MATCH(C37,'Plan de cuentas'!$A$5:$A$55,0)) -> AII1 | M37: =INDEX('Plan de cuentas'!$D$5:$D$55,MATCH(C37,'Plan de cuentas'!$A$5:$A$55,0)) -> -
A38: 14 | B38: 46108 | C38: 4100 | D38: Acreedores por prestaciones de servicios | E38: Cambio titularidad NV200 1370KGF - expediente a nombre de Roberto de Roa (Gestoria Amengual (Miguel Mas Amengual)) | G38: 131.04 | H38: FRR | I38: V1 | J38: 26A900070 Gestoria Amengual (Miguel Mas Amengual) | K38: =F38-G38 -> -131.04 | L38: =INDEX('Plan de cuentas'!$C$5:$C$55,MATCH(C38,'Plan de cuentas'!$A$5:$A$55,0)) -> PCV1 | M38: =INDEX('Plan de cuentas'!$D$5:$D$55,MATCH(C38,'Plan de cuentas'!$A$5:$A$55,0)) -> -
A39: 15 | B39: 46108 | C39: 2180 | D39: Elementos de transporte | E39: Cambio titularidad NV200 1370KGF (suplidos: ITP 152.64 + tasas) (Gestoria Amengual (Miguel Mas Amengual)) | F39: 54 | H39: FRR | I39: V1 | J39: 26A900071 Gestoria Amengual (Miguel Mas Amengual) | K39: =F39-G39 -> 54 | L39: =INDEX('Plan de cuentas'!$C$5:$C$55,MATCH(C39,'Plan de cuentas'!$A$5:$A$55,0)) -> AII1 | M39: =INDEX('Plan de cuentas'!$D$5:$D$55,MATCH(C39,'Plan de cuentas'!$A$5:$A$55,0)) -> -
A40: 15 | B40: 46108 | C40: 4720 | D40: H.P. IVA soportado | E40: IVA soportado 26A900071 Gestoria Amengual (Miguel Mas Amengual) | F40: 11.34 | H40: FRR | I40: V1 | J40: 26A900071 Gestoria Amengual (Miguel Mas Amengual) | K40: =F40-G40 -> 11.34 | L40: =INDEX('Plan de cuentas'!$C$5:$C$55,MATCH(C40,'Plan de cuentas'!$A$5:$A$55,0)) -> BIII2 | M40: =INDEX('Plan de cuentas'!$D$5:$D$55,MATCH(C40,'Plan de cuentas'!$A$5:$A$55,0)) -> -
A41: 15 | B41: 46108 | C41: 2180 | D41: Elementos de transporte | E41: Suplidos: Cambio titularidad NV200 1370KGF (suplidos: ITP 152.64 + tasas) (Gestoria Amengual (Miguel Mas Amengual)) | F41: 223.34 | H41: FRR | I41: V1 | J41: 26A900071 Gestoria Amengual (Miguel Mas Amengual) | K41: =F41-G41 -> 223.34 | L41: =INDEX('Plan de cuentas'!$C$5:$C$55,MATCH(C41,'Plan de cuentas'!$A$5:$A$55,0)) -> AII1 | M41: =INDEX('Plan de cuentas'!$D$5:$D$55,MATCH(C41,'Plan de cuentas'!$A$5:$A$55,0)) -> -
A42: 15 | B42: 46108 | C42: 4100 | D42: Acreedores por prestaciones de servicios | E42: Cambio titularidad NV200 1370KGF (suplidos: ITP 152.64 + tasas) (Gestoria Amengual (Miguel Mas Amengual)) | G42: 288.68 | H42: FRR | I42: V1 | J42: 26A900071 Gestoria Amengual (Miguel Mas Amengual) | K42: =F42-G42 -> -288.68 | L42: =INDEX('Plan de cuentas'!$C$5:$C$55,MATCH(C42,'Plan de cuentas'!$A$5:$A$55,0)) -> PCV1 | M42: =INDEX('Plan de cuentas'!$D$5:$D$55,MATCH(C42,'Plan de cuentas'!$A$5:$A$55,0)) -> -
A43: 16 | B43: 46108 | C43: 4100 | D43: Acreedores por prestaciones de servicios | E43: Pago 26A900069 Gestoria Amengual (Miguel Mas Amengual) | F43: 368.04 | H43: PAG | I43: V3 | J43: 26A900069 Gestoria Amengual (Miguel Mas Amengual) | K43: =F43-G43 -> 368.04 | L43: =INDEX('Plan de cuentas'!$C$5:$C$55,MATCH(C43,'Plan de cuentas'!$A$5:$A$55,0)) -> PCV1 | M43: =INDEX('Plan de cuentas'!$D$5:$D$55,MATCH(C43,'Plan de cuentas'!$A$5:$A$55,0)) -> -
A44: 16 | B44: 46108 | C44: 5720 | D44: Bancos c/c BBVA | E44: Pago 26A900069 Gestoria Amengual (Miguel Mas Amengual) | G44: 368.04 | H44: PAG | I44: V3 | J44: 26A900069 Gestoria Amengual (Miguel Mas Amengual) | K44: =F44-G44 -> -368.04 | L44: =INDEX('Plan de cuentas'!$C$5:$C$55,MATCH(C44,'Plan de cuentas'!$A$5:$A$55,0)) -> BVII | M44: =INDEX('Plan de cuentas'!$D$5:$D$55,MATCH(C44,'Plan de cuentas'!$A$5:$A$55,0)) -> -
A45: 17 | B45: 46108 | C45: 4100 | D45: Acreedores por prestaciones de servicios | E45: Pago 26A900070 Gestoria Amengual (Miguel Mas Amengual) | F45: 131.04 | H45: PAG | I45: V1 | J45: 26A900070 Gestoria Amengual (Miguel Mas Amengual) | K45: =F45-G45 -> 131.04 | L45: =INDEX('Plan de cuentas'!$C$5:$C$55,MATCH(C45,'Plan de cuentas'!$A$5:$A$55,0)) -> PCV1 | M45: =INDEX('Plan de cuentas'!$D$5:$D$55,MATCH(C45,'Plan de cuentas'!$A$5:$A$55,0)) -> -
A46: 17 | B46: 46108 | C46: 5720 | D46: Bancos c/c BBVA | E46: Pago 26A900070 Gestoria Amengual (Miguel Mas Amengual) | G46: 131.04 | H46: PAG | I46: V1 | J46: 26A900070 Gestoria Amengual (Miguel Mas Amengual) | K46: =F46-G46 -> -131.04 | L46: =INDEX('Plan de cuentas'!$C$5:$C$55,MATCH(C46,'Plan de cuentas'!$A$5:$A$55,0)) -> BVII | M46: =INDEX('Plan de cuentas'!$D$5:$D$55,MATCH(C46,'Plan de cuentas'!$A$5:$A$55,0)) -> -
A47: 18 | B47: 46108 | C47: 4100 | D47: Acreedores por prestaciones de servicios | E47: Pago 26A900071 Gestoria Amengual (Miguel Mas Amengual) | F47: 288.68 | H47: PAG | I47: V1 | J47: 26A900071 Gestoria Amengual (Miguel Mas Amengual) | K47: =F47-G47 -> 288.68 | L47: =INDEX('Plan de cuentas'!$C$5:$C$55,MATCH(C47,'Plan de cuentas'!$A$5:$A$55,0)) -> PCV1 | M47: =INDEX('Plan de cuentas'!$D$5:$D$55,MATCH(C47,'Plan de cuentas'!$A$5:$A$55,0)) -> -
A48: 18 | B48: 46108 | C48: 5720 | D48: Bancos c/c BBVA | E48: Pago 26A900071 Gestoria Amengual (Miguel Mas Amengual) | G48: 288.68 | H48: PAG | I48: V1 | J48: 26A900071 Gestoria Amengual (Miguel Mas Amengual) | K48: =F48-G48 -> -288.68 | L48: =INDEX('Plan de cuentas'!$C$5:$C$55,MATCH(C48,'Plan de cuentas'!$A$5:$A$55,0)) -> BVII | M48: =INDEX('Plan de cuentas'!$D$5:$D$55,MATCH(C48,'Plan de cuentas'!$A$5:$A$55,0)) -> -
A49: 19 | B49: 46112 | C49: 6810 | D49: Amortización del inmovilizado material | E49: Amortización Nissan NV200 Furgon 1.5 dCi 90cv 1370KGF (31 días al 16% anual) | F49: 57.03 | H49: AMO | I49: V1 | J49: Amortización V1 03/2026 | K49: =F49-G49 -> 57.03 | L49: =INDEX('Plan de cuentas'!$C$5:$C$55,MATCH(C49,'Plan de cuentas'!$A$5:$A$55,0)) -> PAVII | M49: =INDEX('Plan de cuentas'!$D$5:$D$55,MATCH(C49,'Plan de cuentas'!$A$5:$A$55,0)) -> P8
A50: 19 | B50: 46112 | C50: 2818 | D50: Amortización acumulada de elementos de transporte | E50: Amortización Nissan NV200 Furgon 1.5 dCi 90cv 1370KGF (31 días al 16% anual) | G50: 57.03 | H50: AMO | I50: V1 | J50: Amortización V1 03/2026 | K50: =F50-G50 -> -57.03 | L50: =INDEX('Plan de cuentas'!$C$5:$C$55,MATCH(C50,'Plan de cuentas'!$A$5:$A$55,0)) -> AII3 | M50: =INDEX('Plan de cuentas'!$D$5:$D$55,MATCH(C50,'Plan de cuentas'!$A$5:$A$55,0)) -> -
A51: 20 | B51: 46112 | C51: 6810 | D51: Amortización del inmovilizado material | E51: Amortización Nissan NV200 Furgon 1.5 dCi 90cv 2436KSS (31 días al 16% anual) | F51: 124.91 | H51: AMO | I51: V2 | J51: Amortización V2 03/2026 | K51: =F51-G51 -> 124.91 | L51: =INDEX('Plan de cuentas'!$C$5:$C$55,MATCH(C51,'Plan de cuentas'!$A$5:$A$55,0)) -> PAVII | M51: =INDEX('Plan de cuentas'!$D$5:$D$55,MATCH(C51,'Plan de cuentas'!$A$5:$A$55,0)) -> P8
A52: 20 | B52: 46112 | C52: 2818 | D52: Amortización acumulada de elementos de transporte | E52: Amortización Nissan NV200 Furgon 1.5 dCi 90cv 2436KSS (31 días al 16% anual) | G52: 124.91 | H52: AMO | I52: V2 | J52: Amortización V2 03/2026 | K52: =F52-G52 -> -124.91 | L52: =INDEX('Plan de cuentas'!$C$5:$C$55,MATCH(C52,'Plan de cuentas'!$A$5:$A$55,0)) -> AII3 | M52: =INDEX('Plan de cuentas'!$D$5:$D$55,MATCH(C52,'Plan de cuentas'!$A$5:$A$55,0)) -> -
A53: 21 | B53: 46112 | C53: 6810 | D53: Amortización del inmovilizado material | E53: Amortización Ford Fiesta 4161JHF (28 días al 16% anual) | F53: 75.57 | H53: AMO | I53: V3 | J53: Amortización V3 03/2026 | K53: =F53-G53 -> 75.57 | L53: =INDEX('Plan de cuentas'!$C$5:$C$55,MATCH(C53,'Plan de cuentas'!$A$5:$A$55,0)) -> PAVII | M53: =INDEX('Plan de cuentas'!$D$5:$D$55,MATCH(C53,'Plan de cuentas'!$A$5:$A$55,0)) -> P8
A54: 21 | B54: 46112 | C54: 2818 | D54: Amortización acumulada de elementos de transporte | E54: Amortización Ford Fiesta 4161JHF (28 días al 16% anual) | G54: 75.57 | H54: AMO | I54: V3 | J54: Amortización V3 03/2026 | K54: =F54-G54 -> -75.57 | L54: =INDEX('Plan de cuentas'!$C$5:$C$55,MATCH(C54,'Plan de cuentas'!$A$5:$A$55,0)) -> AII3 | M54: =INDEX('Plan de cuentas'!$D$5:$D$55,MATCH(C54,'Plan de cuentas'!$A$5:$A$55,0)) -> -
A55: 22 | B55: 46112 | C55: 4720 | D55: H.P. IVA soportado | E55: Liquidación IVA 2026-T1 | G55: 236.54 | H55: IVA | J55: Modelo 303 2026-T1 | K55: =F55-G55 -> -236.54 | L55: =INDEX('Plan de cuentas'!$C$5:$C$55,MATCH(C55,'Plan de cuentas'!$A$5:$A$55,0)) -> BIII2 | M55: =INDEX('Plan de cuentas'!$D$5:$D$55,MATCH(C55,'Plan de cuentas'!$A$5:$A$55,0)) -> -
A56: 22 | B56: 46112 | C56: 4700 | D56: H.P. deudora por IVA (a compensar) | E56: IVA a compensar 2026-T1 (modelo 303) | F56: 236.54 | H56: IVA | J56: Modelo 303 2026-T1 | K56: =F56-G56 -> 236.54 | L56: =INDEX('Plan de cuentas'!$C$5:$C$55,MATCH(C56,'Plan de cuentas'!$A$5:$A$55,0)) -> BIII2 | M56: =INDEX('Plan de cuentas'!$D$5:$D$55,MATCH(C56,'Plan de cuentas'!$A$5:$A$55,0)) -> -
A57: 23 | B57: 46118 | C57: 6290 | D57: Otros servicios | E57: Hosting Plan Mini + dominio bertssolutions.com (1 ano) (Webempresa Europa SLU) | F57: 34.36 | H57: FRR | J57: F26-45941 Webempresa Europa SLU | K57: =F57-G57 -> 34.36 | L57: =INDEX('Plan de cuentas'!$C$5:$C$55,MATCH(C57,'Plan de cuentas'!$A$5:$A$55,0)) -> PAVII | M57: =INDEX('Plan de cuentas'!$D$5:$D$55,MATCH(C57,'Plan de cuentas'!$A$5:$A$55,0)) -> P7a
A58: 23 | B58: 46118 | C58: 4100 | D58: Acreedores por prestaciones de servicios | E58: Hosting Plan Mini + dominio bertssolutions.com (1 ano) (Webempresa Europa SLU) | G58: 34.36 | H58: FRR | J58: F26-45941 Webempresa Europa SLU | K58: =F58-G58 -> -34.36 | L58: =INDEX('Plan de cuentas'!$C$5:$C$55,MATCH(C58,'Plan de cuentas'!$A$5:$A$55,0)) -> PCV1 | M58: =INDEX('Plan de cuentas'!$D$5:$D$55,MATCH(C58,'Plan de cuentas'!$A$5:$A$55,0)) -> -
A59: 24 | B59: 46118 | C59: 4100 | D59: Acreedores por prestaciones de servicios | E59: Pago F26-45941 Webempresa Europa SLU | F59: 34.36 | H59: PAG | J59: F26-45941 Webempresa Europa SLU | K59: =F59-G59 -> 34.36 | L59: =INDEX('Plan de cuentas'!$C$5:$C$55,MATCH(C59,'Plan de cuentas'!$A$5:$A$55,0)) -> PCV1 | M59: =INDEX('Plan de cuentas'!$D$5:$D$55,MATCH(C59,'Plan de cuentas'!$A$5:$A$55,0)) -> -
A60: 24 | B60: 46118 | C60: 5720 | D60: Bancos c/c BBVA | E60: Pago F26-45941 Webempresa Europa SLU | G60: 34.36 | H60: PAG | J60: F26-45941 Webempresa Europa SLU | K60: =F60-G60 -> -34.36 | L60: =INDEX('Plan de cuentas'!$C$5:$C$55,MATCH(C60,'Plan de cuentas'!$A$5:$A$55,0)) -> BVII | M60: =INDEX('Plan de cuentas'!$D$5:$D$55,MATCH(C60,'Plan de cuentas'!$A$5:$A$55,0)) -> -
A61: 25 | B61: 46118 | C61: 4300 | D61: Clientes | E61: Alquiler vehiculo comercial Nissan NV200 - mes de abril (Cielo Elizabeth Castillo Gomez) | F61: 700 | H61: FRE | I61: V2 | J61: Factura 9 Cielo Elizabeth Castillo Gomez | K61: =F61-G61 -> 700 | L61: =INDEX('Plan de cuentas'!$C$5:$C$55,MATCH(C61,'Plan de cuentas'!$A$5:$A$55,0)) -> BIII1 | M61: =INDEX('Plan de cuentas'!$D$5:$D$55,MATCH(C61,'Plan de cuentas'!$A$5:$A$55,0)) -> -
A62: 25 | B62: 46118 | C62: 7050 | D62: Prestaciones de servicios (alquileres) | E62: Alquiler vehiculo comercial Nissan NV200 - mes de abril (Cielo Elizabeth Castillo Gomez) | G62: 578.51 | H62: FRE | I62: V2 | J62: Factura 9 Cielo Elizabeth Castillo Gomez | K62: =F62-G62 -> -578.51 | L62: =INDEX('Plan de cuentas'!$C$5:$C$55,MATCH(C62,'Plan de cuentas'!$A$5:$A$55,0)) -> PAVII | M62: =INDEX('Plan de cuentas'!$D$5:$D$55,MATCH(C62,'Plan de cuentas'!$A$5:$A$55,0)) -> P1
A63: 25 | B63: 46118 | C63: 4770 | D63: H.P. IVA repercutido | E63: IVA repercutido Factura 9 Cielo Elizabeth Castillo Gomez | G63: 121.49 | H63: FRE | I63: V2 | J63: Factura 9 Cielo Elizabeth Castillo Gomez | K63: =F63-G63 -> -121.49 | L63: =INDEX('Plan de cuentas'!$C$5:$C$55,MATCH(C63,'Plan de cuentas'!$A$5:$A$55,0)) -> PCV2 | M63: =INDEX('Plan de cuentas'!$D$5:$D$55,MATCH(C63,'Plan de cuentas'!$A$5:$A$55,0)) -> -
A64: 26 | B64: 46122 | C64: 4300 | D64: Clientes | E64: Alquiler NV200 por plataforma Amovens 09/04 (Hugo Quispe Uscamayta (via Amovens)) | F64: 37.3 | H64: FRE | I64: V1 | J64: Factura A-2026-075757 Hugo Quispe Uscamayta (via Amovens) | K64: =F64-G64 -> 37.3 | L64: =INDEX('Plan de cuentas'!$C$5:$C$55,MATCH(C64,'Plan de cuentas'!$A$5:$A$55,0)) -> BIII1 | M64: =INDEX('Plan de cuentas'!$D$5:$D$55,MATCH(C64,'Plan de cuentas'!$A$5:$A$55,0)) -> -
A65: 26 | B65: 46122 | C65: 7050 | D65: Prestaciones de servicios (alquileres) | E65: Alquiler NV200 por plataforma Amovens 09/04 (Hugo Quispe Uscamayta (via Amovens)) | G65: 30.83 | H65: FRE | I65: V1 | J65: Factura A-2026-075757 Hugo Quispe Uscamayta (via Amovens) | K65: =F65-G65 -> -30.83 | L65: =INDEX('Plan de cuentas'!$C$5:$C$55,MATCH(C65,'Plan de cuentas'!$A$5:$A$55,0)) -> PAVII | M65: =INDEX('Plan de cuentas'!$D$5:$D$55,MATCH(C65,'Plan de cuentas'!$A$5:$A$55,0)) -> P1
A66: 26 | B66: 46122 | C66: 4770 | D66: H.P. IVA repercutido | E66: IVA repercutido Factura A-2026-075757 Hugo Quispe Uscamayta (via Amovens) | G66: 6.47 | H66: FRE | I66: V1 | J66: Factura A-2026-075757 Hugo Quispe Uscamayta (via Amovens) | K66: =F66-G66 -> -6.47 | L66: =INDEX('Plan de cuentas'!$C$5:$C$55,MATCH(C66,'Plan de cuentas'!$A$5:$A$55,0)) -> PCV2 | M66: =INDEX('Plan de cuentas'!$D$5:$D$55,MATCH(C66,'Plan de cuentas'!$A$5:$A$55,0)) -> -
A67: 27 | B67: 46122 | C67: 5720 | D67: Bancos c/c BBVA | E67: Cobro Factura A-2026-075757 Hugo Quispe Uscamayta (via Amovens) | F67: 37.3 | H67: COB | I67: V1 | J67: Factura A-2026-075757 Hugo Quispe Uscamayta (via Amovens) | K67: =F67-G67 -> 37.3 | L67: =INDEX('Plan de cuentas'!$C$5:$C$55,MATCH(C67,'Plan de cuentas'!$A$5:$A$55,0)) -> BVII | M67: =INDEX('Plan de cuentas'!$D$5:$D$55,MATCH(C67,'Plan de cuentas'!$A$5:$A$55,0)) -> -
A68: 27 | B68: 46122 | C68: 4300 | D68: Clientes | E68: Cobro Factura A-2026-075757 Hugo Quispe Uscamayta (via Amovens) | G68: 37.3 | H68: COB | I68: V1 | J68: Factura A-2026-075757 Hugo Quispe Uscamayta (via Amovens) | K68: =F68-G68 -> -37.3 | L68: =INDEX('Plan de cuentas'!$C$5:$C$55,MATCH(C68,'Plan de cuentas'!$A$5:$A$55,0)) -> BIII1 | M68: =INDEX('Plan de cuentas'!$D$5:$D$55,MATCH(C68,'Plan de cuentas'!$A$5:$A$55,0)) -> -
A69: 28 | B69: 46126 | C69: 4300 | D69: Clientes | E69: Alquiler NV200 por plataforma Amovens 13/04 (Hugo Quispe Uscamayta (via Amovens)) | F69: 27.95 | H69: FRE | I69: V1 | J69: Factura A-2026-079507 Hugo Quispe Uscamayta (via Amovens) | K69: =F69-G69 -> 27.95 | L69: =INDEX('Plan de cuentas'!$C$5:$C$55,MATCH(C69,'Plan de cuentas'!$A$5:$A$55,0)) -> BIII1 | M69: =INDEX('Plan de cuentas'!$D$5:$D$55,MATCH(C69,'Plan de cuentas'!$A$5:$A$55,0)) -> -
A70: 28 | B70: 46126 | C70: 7050 | D70: Prestaciones de servicios (alquileres) | E70: Alquiler NV200 por plataforma Amovens 13/04 (Hugo Quispe Uscamayta (via Amovens)) | G70: 23.1 | H70: FRE | I70: V1 | J70: Factura A-2026-079507 Hugo Quispe Uscamayta (via Amovens) | K70: =F70-G70 -> -23.1 | L70: =INDEX('Plan de cuentas'!$C$5:$C$55,MATCH(C70,'Plan de cuentas'!$A$5:$A$55,0)) -> PAVII | M70: =INDEX('Plan de cuentas'!$D$5:$D$55,MATCH(C70,'Plan de cuentas'!$A$5:$A$55,0)) -> P1
A71: 28 | B71: 46126 | C71: 4770 | D71: H.P. IVA repercutido | E71: IVA repercutido Factura A-2026-079507 Hugo Quispe Uscamayta (via Amovens) | G71: 4.85 | H71: FRE | I71: V1 | J71: Factura A-2026-079507 Hugo Quispe Uscamayta (via Amovens) | K71: =F71-G71 -> -4.85 | L71: =INDEX('Plan de cuentas'!$C$5:$C$55,MATCH(C71,'Plan de cuentas'!$A$5:$A$55,0)) -> PCV2 | M71: =INDEX('Plan de cuentas'!$D$5:$D$55,MATCH(C71,'Plan de cuentas'!$A$5:$A$55,0)) -> -
A72: 29 | B72: 46126 | C72: 5720 | D72: Bancos c/c BBVA | E72: Cobro Factura A-2026-079507 Hugo Quispe Uscamayta (via Amovens) | F72: 27.95 | H72: COB | I72: V1 | J72: Factura A-2026-079507 Hugo Quispe Uscamayta (via Amovens) | K72: =F72-G72 -> 27.95 | L72: =INDEX('Plan de cuentas'!$C$5:$C$55,MATCH(C72,'Plan de cuentas'!$A$5:$A$55,0)) -> BVII | M72: =INDEX('Plan de cuentas'!$D$5:$D$55,MATCH(C72,'Plan de cuentas'!$A$5:$A$55,0)) -> -
A73: 29 | B73: 46126 | C73: 4300 | D73: Clientes | E73: Cobro Factura A-2026-079507 Hugo Quispe Uscamayta (via Amovens) | G73: 27.95 | H73: COB | I73: V1 | J73: Factura A-2026-079507 Hugo Quispe Uscamayta (via Amovens) | K73: =F73-G73 -> -27.95 | L73: =INDEX('Plan de cuentas'!$C$5:$C$55,MATCH(C73,'Plan de cuentas'!$A$5:$A$55,0)) -> BIII1 | M73: =INDEX('Plan de cuentas'!$D$5:$D$55,MATCH(C73,'Plan de cuentas'!$A$5:$A$55,0)) -> -
A74: 30 | B74: 46130 | C74: 4300 | D74: Clientes | E74: Alquiler NV200 por plataforma Amovens 17/04 (Hugo Quispe Uscamayta (via Amovens)) | F74: 52.85 | H74: FRE | I74: V1 | J74: Factura A-2026-082625 Hugo Quispe Uscamayta (via Amovens) | K74: =F74-G74 -> 52.85 | L74: =INDEX('Plan de cuentas'!$C$5:$C$55,MATCH(C74,'Plan de cuentas'!$A$5:$A$55,0)) -> BIII1 | M74: =INDEX('Plan de cuentas'!$D$5:$D$55,MATCH(C74,'Plan de cuentas'!$A$5:$A$55,0)) -> -
A75: 30 | B75: 46130 | C75: 7050 | D75: Prestaciones de servicios (alquileres) | E75: Alquiler NV200 por plataforma Amovens 17/04 (Hugo Quispe Uscamayta (via Amovens)) | G75: 43.68 | H75: FRE | I75: V1 | J75: Factura A-2026-082625 Hugo Quispe Uscamayta (via Amovens) | K75: =F75-G75 -> -43.68 | L75: =INDEX('Plan de cuentas'!$C$5:$C$55,MATCH(C75,'Plan de cuentas'!$A$5:$A$55,0)) -> PAVII | M75: =INDEX('Plan de cuentas'!$D$5:$D$55,MATCH(C75,'Plan de cuentas'!$A$5:$A$55,0)) -> P1
A76: 30 | B76: 46130 | C76: 4770 | D76: H.P. IVA repercutido | E76: IVA repercutido Factura A-2026-082625 Hugo Quispe Uscamayta (via Amovens) | G76: 9.17 | H76: FRE | I76: V1 | J76: Factura A-2026-082625 Hugo Quispe Uscamayta (via Amovens) | K76: =F76-G76 -> -9.17 | L76: =INDEX('Plan de cuentas'!$C$5:$C$55,MATCH(C76,'Plan de cuentas'!$A$5:$A$55,0)) -> PCV2 | M76: =INDEX('Plan de cuentas'!$D$5:$D$55,MATCH(C76,'Plan de cuentas'!$A$5:$A$55,0)) -> -
A77: 31 | B77: 46130 | C77: 5720 | D77: Bancos c/c BBVA | E77: Cobro Factura A-2026-082625 Hugo Quispe Uscamayta (via Amovens) | F77: 52.85 | H77: COB | I77: V1 | J77: Factura A-2026-082625 Hugo Quispe Uscamayta (via Amovens) | K77: =F77-G77 -> 52.85 | L77: =INDEX('Plan de cuentas'!$C$5:$C$55,MATCH(C77,'Plan de cuentas'!$A$5:$A$55,0)) -> BVII | M77: =INDEX('Plan de cuentas'!$D$5:$D$55,MATCH(C77,'Plan de cuentas'!$A$5:$A$55,0)) -> -
A78: 31 | B78: 46130 | C78: 4300 | D78: Clientes | E78: Cobro Factura A-2026-082625 Hugo Quispe Uscamayta (via Amovens) | G78: 52.85 | H78: COB | I78: V1 | J78: Factura A-2026-082625 Hugo Quispe Uscamayta (via Amovens) | K78: =F78-G78 -> -52.85 | L78: =INDEX('Plan de cuentas'!$C$5:$C$55,MATCH(C78,'Plan de cuentas'!$A$5:$A$55,0)) -> BIII1 | M78: =INDEX('Plan de cuentas'!$D$5:$D$55,MATCH(C78,'Plan de cuentas'!$A$5:$A$55,0)) -> -
A79: 32 | B79: 46131 | C79: 6310 | D79: Otros tributos (IVTM...) | E79: Impuesto de circulacion (IVTM) 2026 del Ford Fiesta - reembolso a la vendedora (Ayuntamiento El Casar (via reembolso a Ruth Serrano)) | F79: 47.94 | H79: FRR | I79: V3 | J79: IVTM-2026-4161JHF Ayuntamiento El Casar (via reembolso a Ruth Serrano) | K79: =F79-G79 -> 47.94 | L79: =INDEX('Plan de cuentas'!$C$5:$C$55,MATCH(C79,'Plan de cuentas'!$A$5:$A$55,0)) -> PAVII | M79: =INDEX('Plan de cuentas'!$D$5:$D$55,MATCH(C79,'Plan de cuentas'!$A$5:$A$55,0)) -> P7b
A80: 32 | B80: 46131 | C80: 4100 | D80: Acreedores por prestaciones de servicios | E80: Impuesto de circulacion (IVTM) 2026 del Ford Fiesta - reembolso a la vendedora (Ayuntamiento El Casar (via reembolso a Ruth Serrano)) | G80: 47.94 | H80: FRR | I80: V3 | J80: IVTM-2026-4161JHF Ayuntamiento El Casar (via reembolso a Ruth Serrano) | K80: =F80-G80 -> -47.94 | L80: =INDEX('Plan de cuentas'!$C$5:$C$55,MATCH(C80,'Plan de cuentas'!$A$5:$A$55,0)) -> PCV1 | M80: =INDEX('Plan de cuentas'!$D$5:$D$55,MATCH(C80,'Plan de cuentas'!$A$5:$A$55,0)) -> -
A81: 33 | B81: 46131 | C81: 4100 | D81: Acreedores por prestaciones de servicios | E81: Pago IVTM-2026-4161JHF Ayuntamiento El Casar (via reembolso a Ruth Serrano) | F81: 47.94 | H81: PAG | I81: V3 | J81: IVTM-2026-4161JHF Ayuntamiento El Casar (via reembolso a Ruth Serrano) | K81: =F81-G81 -> 47.94 | L81: =INDEX('Plan de cuentas'!$C$5:$C$55,MATCH(C81,'Plan de cuentas'!$A$5:$A$55,0)) -> PCV1 | M81: =INDEX('Plan de cuentas'!$D$5:$D$55,MATCH(C81,'Plan de cuentas'!$A$5:$A$55,0)) -> -
A82: 33 | B82: 46131 | C82: 5720 | D82: Bancos c/c BBVA | E82: Pago IVTM-2026-4161JHF Ayuntamiento El Casar (via reembolso a Ruth Serrano) | G82: 47.94 | H82: PAG | I82: V3 | J82: IVTM-2026-4161JHF Ayuntamiento El Casar (via reembolso a Ruth Serrano) | K82: =F82-G82 -> -47.94 | L82: =INDEX('Plan de cuentas'!$C$5:$C$55,MATCH(C82,'Plan de cuentas'!$A$5:$A$55,0)) -> BVII | M82: =INDEX('Plan de cuentas'!$D$5:$D$55,MATCH(C82,'Plan de cuentas'!$A$5:$A$55,0)) -> -
A83: 34 | B83: 46131 | C83: 4300 | D83: Clientes | E83: Alquiler vehiculo comercial Nissan NV200 19/04-19/05 (David Chaves Jodar) | F83: 700 | H83: FRE | J83: Factura 10 David Chaves Jodar | K83: =F83-G83 -> 700 | L83: =INDEX('Plan de cuentas'!$C$5:$C$55,MATCH(C83,'Plan de cuentas'!$A$5:$A$55,0)) -> BIII1 | M83: =INDEX('Plan de cuentas'!$D$5:$D$55,MATCH(C83,'Plan de cuentas'!$A$5:$A$55,0)) -> -
A84: 34 | B84: 46131 | C84: 7050 | D84: Prestaciones de servicios (alquileres) | E84: Alquiler vehiculo comercial Nissan NV200 19/04-19/05 (David Chaves Jodar) | G84: 578.51 | H84: FRE | J84: Factura 10 David Chaves Jodar | K84: =F84-G84 -> -578.51 | L84: =INDEX('Plan de cuentas'!$C$5:$C$55,MATCH(C84,'Plan de cuentas'!$A$5:$A$55,0)) -> PAVII | M84: =INDEX('Plan de cuentas'!$D$5:$D$55,MATCH(C84,'Plan de cuentas'!$A$5:$A$55,0)) -> P1
A85: 34 | B85: 46131 | C85: 4770 | D85: H.P. IVA repercutido | E85: IVA repercutido Factura 10 David Chaves Jodar | G85: 121.49 | H85: FRE | J85: Factura 10 David Chaves Jodar | K85: =F85-G85 -> -121.49 | L85: =INDEX('Plan de cuentas'!$C$5:$C$55,MATCH(C85,'Plan de cuentas'!$A$5:$A$55,0)) -> PCV2 | M85: =INDEX('Plan de cuentas'!$D$5:$D$55,MATCH(C85,'Plan de cuentas'!$A$5:$A$55,0)) -> -
A86: 35 | B86: 46142 | C86: 6810 | D86: Amortización del inmovilizado material | E86: Amortización Nissan NV200 Furgon 1.5 dCi 90cv 1370KGF (30 días al 16% anual) | F86: 55.19 | H86: AMO | I86: V1 | J86: Amortización V1 04/2026 | K86: =F86-G86 -> 55.19 | L86: =INDEX('Plan de cuentas'!$C$5:$C$55,MATCH(C86,'Plan de cuentas'!$A$5:$A$55,0)) -> PAVII | M86: =INDEX('Plan de cuentas'!$D$5:$D$55,MATCH(C86,'Plan de cuentas'!$A$5:$A$55,0)) -> P8
A87: 35 | B87: 46142 | C87: 2818 | D87: Amortización acumulada de elementos de transporte | E87: Amortización Nissan NV200 Furgon 1.5 dCi 90cv 1370KGF (30 días al 16% anual) | G87: 55.19 | H87: AMO | I87: V1 | J87: Amortización V1 04/2026 | K87: =F87-G87 -> -55.19 | L87: =INDEX('Plan de cuentas'!$C$5:$C$55,MATCH(C87,'Plan de cuentas'!$A$5:$A$55,0)) -> AII3 | M87: =INDEX('Plan de cuentas'!$D$5:$D$55,MATCH(C87,'Plan de cuentas'!$A$5:$A$55,0)) -> -
A88: 36 | B88: 46142 | C88: 6810 | D88: Amortización del inmovilizado material | E88: Amortización Nissan NV200 Furgon 1.5 dCi 90cv 2436KSS (30 días al 16% anual) | F88: 120.88 | H88: AMO | I88: V2 | J88: Amortización V2 04/2026 | K88: =F88-G88 -> 120.88 | L88: =INDEX('Plan de cuentas'!$C$5:$C$55,MATCH(C88,'Plan de cuentas'!$A$5:$A$55,0)) -> PAVII | M88: =INDEX('Plan de cuentas'!$D$5:$D$55,MATCH(C88,'Plan de cuentas'!$A$5:$A$55,0)) -> P8
A89: 36 | B89: 46142 | C89: 2818 | D89: Amortización acumulada de elementos de transporte | E89: Amortización Nissan NV200 Furgon 1.5 dCi 90cv 2436KSS (30 días al 16% anual) | G89: 120.88 | H89: AMO | I89: V2 | J89: Amortización V2 04/2026 | K89: =F89-G89 -> -120.88 | L89: =INDEX('Plan de cuentas'!$C$5:$C$55,MATCH(C89,'Plan de cuentas'!$A$5:$A$55,0)) -> AII3 | M89: =INDEX('Plan de cuentas'!$D$5:$D$55,MATCH(C89,'Plan de cuentas'!$A$5:$A$55,0)) -> -
A90: 37 | B90: 46142 | C90: 6810 | D90: Amortización del inmovilizado material | E90: Amortización Ford Fiesta 4161JHF (30 días al 16% anual) | F90: 80.96 | H90: AMO | I90: V3 | J90: Amortización V3 04/2026 | K90: =F90-G90 -> 80.96 | L90: =INDEX('Plan de cuentas'!$C$5:$C$55,MATCH(C90,'Plan de cuentas'!$A$5:$A$55,0)) -> PAVII | M90: =INDEX('Plan de cuentas'!$D$5:$D$55,MATCH(C90,'Plan de cuentas'!$A$5:$A$55,0)) -> P8
A91: 37 | B91: 46142 | C91: 2818 | D91: Amortización acumulada de elementos de transporte | E91: Amortización Ford Fiesta 4161JHF (30 días al 16% anual) | G91: 80.96 | H91: AMO | I91: V3 | J91: Amortización V3 04/2026 | K91: =F91-G91 -> -80.96 | L91: =INDEX('Plan de cuentas'!$C$5:$C$55,MATCH(C91,'Plan de cuentas'!$A$5:$A$55,0)) -> AII3 | M91: =INDEX('Plan de cuentas'!$D$5:$D$55,MATCH(C91,'Plan de cuentas'!$A$5:$A$55,0)) -> -
A92: 38 | B92: 46148 | C92: 2180 | D92: Elementos de transporte | E92: Compra Ford Mustang 2.3L (Blanco) P7559BDR (temporal) a ECOM HOLDING LLC FZ | F92: 6967.03 | H92: COM | I92: V4 | K92: =F92-G92 -> 6967.03 | L92: =INDEX('Plan de cuentas'!$C$5:$C$55,MATCH(C92,'Plan de cuentas'!$A$5:$A$55,0)) -> AII1 | M92: =INDEX('Plan de cuentas'!$D$5:$D$55,MATCH(C92,'Plan de cuentas'!$A$5:$A$55,0)) -> -
A93: 38 | B93: 46148 | C93: 5550 | D93: Partidas pendientes de aplicación | E93: Compra Ford Mustang 2.3L (Blanco) P7559BDR (temporal) a ECOM HOLDING LLC FZ | G93: 6967.03 | H93: COM | I93: V4 | K93: =F93-G93 -> -6967.03 | L93: =INDEX('Plan de cuentas'!$C$5:$C$55,MATCH(C93,'Plan de cuentas'!$A$5:$A$55,0)) -> D555 | M93: =INDEX('Plan de cuentas'!$D$5:$D$55,MATCH(C93,'Plan de cuentas'!$A$5:$A$55,0)) -> -
A94: 39 | B94: 46148 | C94: 2180 | D94: Elementos de transporte | E94: Suplidos DUA importacion Mustang Blanco (arancel + IVA importacion sin desglosar) (Amalgama Export SL) | F94: 2411.23 | H94: FRR | I94: V4 | J94: AES2600140 Amalgama Export SL | K94: =F94-G94 -> 2411.23 | L94: =INDEX('Plan de cuentas'!$C$5:$C$55,MATCH(C94,'Plan de cuentas'!$A$5:$A$55,0)) -> AII1 | M94: =INDEX('Plan de cuentas'!$D$5:$D$55,MATCH(C94,'Plan de cuentas'!$A$5:$A$55,0)) -> -
A95: 39 | B95: 46148 | C95: 4100 | D95: Acreedores por prestaciones de servicios | E95: Suplidos DUA importacion Mustang Blanco (arancel + IVA importacion sin desglosar) (Amalgama Export SL) | G95: 2411.23 | H95: FRR | I95: V4 | J95: AES2600140 Amalgama Export SL | K95: =F95-G95 -> -2411.23 | L95: =INDEX('Plan de cuentas'!$C$5:$C$55,MATCH(C95,'Plan de cuentas'!$A$5:$A$55,0)) -> PCV1 | M95: =INDEX('Plan de cuentas'!$D$5:$D$55,MATCH(C95,'Plan de cuentas'!$A$5:$A$55,0)) -> -
A96: 40 | B96: 46148 | C96: 4100 | D96: Acreedores por prestaciones de servicios | E96: Pago AES2600140 Amalgama Export SL | F96: 2411.23 | H96: PAG | I96: V4 | J96: AES2600140 Amalgama Export SL | K96: =F96-G96 -> 2411.23 | L96: =INDEX('Plan de cuentas'!$C$5:$C$55,MATCH(C96,'Plan de cuentas'!$A$5:$A$55,0)) -> PCV1 | M96: =INDEX('Plan de cuentas'!$D$5:$D$55,MATCH(C96,'Plan de cuentas'!$A$5:$A$55,0)) -> -
A97: 40 | B97: 46148 | C97: 5720 | D97: Bancos c/c BBVA | E97: Pago AES2600140 Amalgama Export SL | G97: 2411.23 | H97: PAG | I97: V4 | J97: AES2600140 Amalgama Export SL | K97: =F97-G97 -> -2411.23 | L97: =INDEX('Plan de cuentas'!$C$5:$C$55,MATCH(C97,'Plan de cuentas'!$A$5:$A$55,0)) -> BVII | M97: =INDEX('Plan de cuentas'!$D$5:$D$55,MATCH(C97,'Plan de cuentas'!$A$5:$A$55,0)) -> -
A98: 41 | B98: 46155 | C98: 2180 | D98: Elementos de transporte | E98: Gastos importacion Mustang Blanco: naviera escaner despacho transporte descarga (Amalgama Export SL) | F98: 1010 | H98: FRR | I98: V4 | J98: AEF2600244 Amalgama Export SL | K98: =F98-G98 -> 1010 | L98: =INDEX('Plan de cuentas'!$C$5:$C$55,MATCH(C98,'Plan de cuentas'!$A$5:$A$55,0)) -> AII1 | M98: =INDEX('Plan de cuentas'!$D$5:$D$55,MATCH(C98,'Plan de cuentas'!$A$5:$A$55,0)) -> -
A99: 41 | B99: 46155 | C99: 4720 | D99: H.P. IVA soportado | E99: IVA soportado AEF2600244 Amalgama Export SL | F99: 212.1 | H99: FRR | I99: V4 | J99: AEF2600244 Amalgama Export SL | K99: =F99-G99 -> 212.1 | L99: =INDEX('Plan de cuentas'!$C$5:$C$55,MATCH(C99,'Plan de cuentas'!$A$5:$A$55,0)) -> BIII2 | M99: =INDEX('Plan de cuentas'!$D$5:$D$55,MATCH(C99,'Plan de cuentas'!$A$5:$A$55,0)) -> -
A100: 41 | B100: 46155 | C100: 4100 | D100: Acreedores por prestaciones de servicios | E100: Gastos importacion Mustang Blanco: naviera escaner despacho transporte descarga (Amalgama Export SL) | G100: 1222.1 | H100: FRR | I100: V4 | J100: AEF2600244 Amalgama Export SL | K100: =F100-G100 -> -1222.1 | L100: =INDEX('Plan de cuentas'!$C$5:$C$55,MATCH(C100,'Plan de cuentas'!$A$5:$A$55,0)) -> PCV1 | M100: =INDEX('Plan de cuentas'!$D$5:$D$55,MATCH(C100,'Plan de cuentas'!$A$5:$A$55,0)) -> -
...

Sheet Sumas y saldos
A1: Balance de sumas y saldos
A2: Movimientos acumulados de cada cuenta hasta la fecha de corte.
A4: Cuenta | B4: Nombre | C4: Debe (€) | D4: Haber (€) | E4: Saldo deudor (€) | F4: Saldo acreedor (€)
A5: 1000 | B5: Capital social | C5: =SUMIFS(Diario!$F$2:$F$229,Diario!$C$2:$C$229,$A5,Diario!$B$2:$B$229,"<="&FechaCorte) -> 0 | D5: =SUMIFS(Diario!$G$2:$G$229,Diario!$C$2:$C$229,$A5,Diario!$B$2:$B$229,"<="&FechaCorte) -> 3100 | E5: =MAX(0,C5-D5) -> 0 | F5: =MAX(0,D5-C5) -> 3100
A6: 1120 | B6: Reserva legal | C6: =SUMIFS(Diario!$F$2:$F$229,Diario!$C$2:$C$229,$A6,Diario!$B$2:$B$229,"<="&FechaCorte) -> 0 | D6: =SUMIFS(Diario!$G$2:$G$229,Diario!$C$2:$C$229,$A6,Diario!$B$2:$B$229,"<="&FechaCorte) -> 6.49 | E6: =MAX(0,C6-D6) -> 0 | F6: =MAX(0,D6-C6) -> 6.49
A7: 1180 | B7: Aportaciones de socios o propietarios | C7: =SUMIFS(Diario!$F$2:$F$229,Diario!$C$2:$C$229,$A7,Diario!$B$2:$B$229,"<="&FechaCorte) -> 0 | D7: =SUMIFS(Diario!$G$2:$G$229,Diario!$C$2:$C$229,$A7,Diario!$B$2:$B$229,"<="&FechaCorte) -> 72153.73 | E7: =MAX(0,C7-D7) -> 0 | F7: =MAX(0,D7-C7) -> 72153.73
A8: 1200 | B8: Remanente | C8: =SUMIFS(Diario!$F$2:$F$229,Diario!$C$2:$C$229,$A8,Diario!$B$2:$B$229,"<="&FechaCorte) -> 0 | D8: =SUMIFS(Diario!$G$2:$G$229,Diario!$C$2:$C$229,$A8,Diario!$B$2:$B$229,"<="&FechaCorte) -> 58.39 | E8: =MAX(0,C8-D8) -> 0 | F8: =MAX(0,D8-C8) -> 58.39
A9: 1290 | B9: Resultado del ejercicio | C9: =SUMIFS(Diario!$F$2:$F$229,Diario!$C$2:$C$229,$A9,Diario!$B$2:$B$229,"<="&FechaCorte) -> 64.88 | D9: =SUMIFS(Diario!$G$2:$G$229,Diario!$C$2:$C$229,$A9,Diario!$B$2:$B$229,"<="&FechaCorte) -> 64.88 | E9: =MAX(0,C9-D9) -> 0 | F9: =MAX(0,D9-C9) -> 0
A10: 2130 | B10: Maquinaria | C10: =SUMIFS(Diario!$F$2:$F$229,Diario!$C$2:$C$229,$A10,Diario!$B$2:$B$229,"<="&FechaCorte) -> 9192 | D10: =SUMIFS(Diario!$G$2:$G$229,Diario!$C$2:$C$229,$A10,Diario!$B$2:$B$229,"<="&FechaCorte) -> 9192 | E10: =MAX(0,C10-D10) -> 0 | F10: =MAX(0,D10-C10) -> 0
A11: 2180 | B11: Elementos de transporte | C11: =SUMIFS(Diario!$F$2:$F$229,Diario!$C$2:$C$229,$A11,Diario!$B$2:$B$229,"<="&FechaCorte) -> 39947.63 | D11: =SUMIFS(Diario!$G$2:$G$229,Diario!$C$2:$C$229,$A11,Diario!$B$2:$B$229,"<="&FechaCorte) -> 6156.7 | E11: =MAX(0,C11-D11) -> 33790.93 | F11: =MAX(0,D11-C11) -> 0
A12: 2818 | B12: Amortización acumulada de elementos de transporte | C12: =SUMIFS(Diario!$F$2:$F$229,Diario!$C$2:$C$229,$A12,Diario!$B$2:$B$229,"<="&FechaCorte) -> 261.78 | D12: =SUMIFS(Diario!$G$2:$G$229,Diario!$C$2:$C$229,$A12,Diario!$B$2:$B$229,"<="&FechaCorte) -> 1711.87 | E12: =MAX(0,C12-D12) -> 0 | F12: =MAX(0,D12-C12) -> 1450.09
A13: 4100 | B13: Acreedores por prestaciones de servicios | C13: =SUMIFS(Diario!$F$2:$F$229,Diario!$C$2:$C$229,$A13,Diario!$B$2:$B$229,"<="&FechaCorte) -> 13923.39 | D13: =SUMIFS(Diario!$G$2:$G$229,Diario!$C$2:$C$229,$A13,Diario!$B$2:$B$229,"<="&FechaCorte) -> 14564.34 | E13: =MAX(0,C13-D13) -> 0 | F13: =MAX(0,D13-C13) -> 640.95
A14: 4300 | B14: Clientes | C14: =SUMIFS(Diario!$F$2:$F$229,Diario!$C$2:$C$229,$A14,Diario!$B$2:$B$229,"<="&FechaCorte) -> 5103.45 | D14: =SUMIFS(Diario!$G$2:$G$229,Diario!$C$2:$C$229,$A14,Diario!$B$2:$B$229,"<="&FechaCorte) -> 212.6 | E14: =MAX(0,C14-D14) -> 4890.85 | F14: =MAX(0,D14-C14) -> 0
A15: 4700 | B15: H.P. deudora por IVA (a compensar) | C15: =SUMIFS(Diario!$F$2:$F$229,Diario!$C$2:$C$229,$A15,Diario!$B$2:$B$229,"<="&FechaCorte) -> 236.54 | D15: =SUMIFS(Diario!$G$2:$G$229,Diario!$C$2:$C$229,$A15,Diario!$B$2:$B$229,"<="&FechaCorte) -> 236.54 | E15: =MAX(0,C15-D15) -> 0 | F15: =MAX(0,D15-C15) -> 0
A16: 4720 | B16: H.P. IVA soportado | C16: =SUMIFS(Diario!$F$2:$F$229,Diario!$C$2:$C$229,$A16,Diario!$B$2:$B$229,"<="&FechaCorte) -> 3920.54 | D16: =SUMIFS(Diario!$G$2:$G$229,Diario!$C$2:$C$229,$A16,Diario!$B$2:$B$229,"<="&FechaCorte) -> 608.23 | E16: =MAX(0,C16-D16) -> 3312.31 | F16: =MAX(0,D16-C16) -> 0
... A31: 7050 | B31: Prestaciones de servicios (alquileres) | C31: =SUMIFS(Diario!$F$2:$F$229,Diario!$C$2:$C$229,$A31,Diario!$B$2:$B$229,"<="&FechaCorte) -> 0 | D31: =SUMIFS(Diario!$G$2:$G$229,Diario!$C$2:$C$229,$A31,Diario!$B$2:$B$229,"<="&FechaCorte) -> 1737.73 | E31: =MAX(0,C31-D31) -> 0 | F31: =MAX(0,D31-C31) -> 1737.73
B32: TOTALES | C32: =SUM(C5:C31) -> 149395.66 | D32: =SUM(D5:D31) -> 149395.66 | E32: =SUM(E5:E31) -> 103930.43 | F32: =SUM(F5:F31) -> 103930.43

Sheet Plan de cuentas
A1: Plan de cuentas utilizado (PGC Pymes)
A2: Relaciona cada cuenta con su línea del Balance y de la PyG. El Diario la usa para clasificar cada apunte.
A4: Cuenta | B4: Nombre | C4: Línea balance | D4: Línea PyG | E4: Texto línea balance | F4: Texto línea PyG
A5: 1000 | B5: Capital social | C5: PAI | D5: - | E5: I. Capital
A6: 1120 | B6: Reserva legal | C6: PAIII | D6: - | E6: III. Reservas
A7: 1130 | B7: Reservas voluntarias | C7: PAIII | D7: - | E7: III. Reservas
A8: 1180 | B8: Aportaciones de socios o propietarios | C8: PAVI | D8: - | E8: VI. Otras aportaciones de socios
A9: 1200 | B9: Remanente | C9: PAV | D9: - | E9: V. Resultados de ejercicios anteriores
A10: 1210 | B10: Resultados negativos de ejercicios anteriores | C10: PAV | D10: - | E10: V. Resultados de ejercicios anteriores
A11: 1290 | B11: Resultado del ejercicio | C11: PAVII | D11: - | E11: VII. Resultado del ejercicio
A12: 1630 | B12: Otras deudas a l/p con partes vinculadas (préstamo de socios) | C12: PBII | D12: - | E12: II. Deudas a largo plazo (bancos, préstamos de socios)
A13: 1700 | B13: Deudas a l/p con entidades de crédito | C13: PBII | D13: - | E13: II. Deudas a largo plazo (bancos, préstamos de socios)
A14: 2130 | B14: Maquinaria | C14: AII2 | D14: - | E14: Otro inmovilizado material
A15: 2180 | B15: Elementos de transporte | C15: AII1 | D15: - | E15: Elementos de transporte (vehículos)
A16: 2818 | B16: Amortización acumulada de elementos de transporte | C16: AII3 | D16: - | E16: Amortización acumulada
... A33: 5720 | B33: Bancos c/c BBVA | C33: BVII | D33: - | E33: VII. Efectivo y otros activos líquidos equivalentes
A34: 6220 | B34: Reparaciones y conservación | C34: PAVII | D34: P7a | E34: VII. Resultado del ejercicio | F34: a) Servicios exteriores
A35: 6230 | B35: Servicios de profesionales independientes | C35: PAVII | D35: P7a | E35: VII. Resultado del ejercicio | F35: a) Servicios exteriores
A36: 6250 | B36: Primas de seguros | C36: PAVII | D36: P7a | E36: VII. Resultado del ejercicio | F36: a) Servicios exteriores
A37: 6260 | B37: Servicios bancarios | C37: PAVII | D37: P7a | E37: VII. Resultado del ejercicio | F37: a) Servicios exteriores
A38: 6270 | B38: Publicidad y propaganda | C38: PAVII | D38: P7a | E38: VII. Resultado del ejercicio | F38: a) Servicios exteriores
A39: 6280 | B39: Suministros (combustible, luz, teléfono...) | C39: PAVII | D39: P7a | E39: VII. Resultado del ejercicio | F39: a) Servicios exteriores
A40: 6290 | B40: Otros servicios | C40: PAVII | D40: P7a | E40: VII. Resultado del ejercicio | F40: a) Servicios exteriores
A41: 6300 | B41: Impuesto sobre beneficios | C41: PAVII | D41: P17 | E41: VII. Resultado del ejercicio | F41: 17. Impuestos sobre beneficios
A42: 6310 | B42: Otros tributos (IVTM...) | C42: PAVII | D42: P7b | E42: VII. Resultado del ejercicio | F42: b) Tributos
A43: 6400 | B43: Sueldos y salarios | C43: PAVII | D43: P6 | E43: VII. Resultado del ejercicio | F43: 6. Gastos de personal
A44: 6420 | B44: Seguridad Social a cargo de la empresa | C44: PAVII | D44: P6 | E44: VII. Resultado del ejercicio | F44: 6. Gastos de personal
A45: 6620 | B45: Intereses de deudas | C45: PAVII | D45: P14 | E45: VII. Resultado del ejercicio | F45: 14. Gastos financieros
... A55: 7780 | B55: Ingresos excepcionales | C55: PAVII | D55: P12 | E55: VII. Resultado del ejercicio | F55: 12. Otros resultados
